package weibo4android.org.json;

public class Test
{
  // ERROR //
  public static void main(String[] paramArrayOfString)
  {
    // Byte code:
    //   0: new 6	weibo4android/org/json/Test$1Obj
    //   3: dup
    //   4: ldc 18
    //   6: ldc2_w 19
    //   9: iconst_1
    //   10: invokespecial 23	weibo4android/org/json/Test$1Obj:<init>	(Ljava/lang/String;DZ)V
    //   13: astore_0
    //   14: ldc 25
    //   16: invokestatic 31	weibo4android/org/json/XML:toJSONObject	(Ljava/lang/String;)Lweibo4android/org/json/JSONObject;
    //   19: astore_1
    //   20: getstatic 37	java/lang/System:out	Ljava/io/PrintStream;
    //   23: aload_1
    //   24: invokevirtual 43	weibo4android/org/json/JSONObject:toString	()Ljava/lang/String;
    //   27: invokevirtual 49	java/io/PrintStream:println	(Ljava/lang/String;)V
    //   30: new 39	weibo4android/org/json/JSONObject
    //   33: dup
    //   34: ldc 51
    //   36: invokespecial 53	weibo4android/org/json/JSONObject:<init>	(Ljava/lang/String;)V
    //   39: astore_1
    //   40: getstatic 37	java/lang/System:out	Ljava/io/PrintStream;
    //   43: aload_1
    //   44: iconst_4
    //   45: invokevirtual 56	weibo4android/org/json/JSONObject:toString	(I)Ljava/lang/String;
    //   48: invokevirtual 49	java/io/PrintStream:println	(Ljava/lang/String;)V
    //   51: getstatic 37	java/lang/System:out	Ljava/io/PrintStream;
    //   54: aload_1
    //   55: invokestatic 59	weibo4android/org/json/XML:toString	(Ljava/lang/Object;)Ljava/lang/String;
    //   58: invokevirtual 49	java/io/PrintStream:println	(Ljava/lang/String;)V
    //   61: ldc 61
    //   63: invokestatic 31	weibo4android/org/json/XML:toJSONObject	(Ljava/lang/String;)Lweibo4android/org/json/JSONObject;
    //   66: astore_1
    //   67: getstatic 37	java/lang/System:out	Ljava/io/PrintStream;
    //   70: aload_1
    //   71: iconst_4
    //   72: invokevirtual 56	weibo4android/org/json/JSONObject:toString	(I)Ljava/lang/String;
    //   75: invokevirtual 49	java/io/PrintStream:println	(Ljava/lang/String;)V
    //   78: getstatic 37	java/lang/System:out	Ljava/io/PrintStream;
    //   81: invokevirtual 63	java/io/PrintStream:println	()V
    //   84: ldc 61
    //   86: invokestatic 66	weibo4android/org/json/JSONML:toJSONObject	(Ljava/lang/String;)Lweibo4android/org/json/JSONObject;
    //   89: astore_1
    //   90: getstatic 37	java/lang/System:out	Ljava/io/PrintStream;
    //   93: aload_1
    //   94: invokevirtual 43	weibo4android/org/json/JSONObject:toString	()Ljava/lang/String;
    //   97: invokevirtual 49	java/io/PrintStream:println	(Ljava/lang/String;)V
    //   100: getstatic 37	java/lang/System:out	Ljava/io/PrintStream;
    //   103: aload_1
    //   104: invokestatic 69	weibo4android/org/json/JSONML:toString	(Lweibo4android/org/json/JSONObject;)Ljava/lang/String;
    //   107: invokevirtual 49	java/io/PrintStream:println	(Ljava/lang/String;)V
    //   110: getstatic 37	java/lang/System:out	Ljava/io/PrintStream;
    //   113: invokevirtual 63	java/io/PrintStream:println	()V
    //   116: ldc 61
    //   118: invokestatic 73	weibo4android/org/json/JSONML:toJSONArray	(Ljava/lang/String;)Lweibo4android/org/json/JSONArray;
    //   121: astore_1
    //   122: getstatic 37	java/lang/System:out	Ljava/io/PrintStream;
    //   125: aload_1
    //   126: iconst_4
    //   127: invokevirtual 76	weibo4android/org/json/JSONArray:toString	(I)Ljava/lang/String;
    //   130: invokevirtual 49	java/io/PrintStream:println	(Ljava/lang/String;)V
    //   133: getstatic 37	java/lang/System:out	Ljava/io/PrintStream;
    //   136: aload_1
    //   137: invokestatic 79	weibo4android/org/json/JSONML:toString	(Lweibo4android/org/json/JSONArray;)Ljava/lang/String;
    //   140: invokevirtual 49	java/io/PrintStream:println	(Ljava/lang/String;)V
    //   143: getstatic 37	java/lang/System:out	Ljava/io/PrintStream;
    //   146: invokevirtual 63	java/io/PrintStream:println	()V
    //   149: ldc 81
    //   151: invokestatic 66	weibo4android/org/json/JSONML:toJSONObject	(Ljava/lang/String;)Lweibo4android/org/json/JSONObject;
    //   154: astore_1
    //   155: getstatic 37	java/lang/System:out	Ljava/io/PrintStream;
    //   158: aload_1
    //   159: iconst_4
    //   160: invokevirtual 56	weibo4android/org/json/JSONObject:toString	(I)Ljava/lang/String;
    //   163: invokevirtual 49	java/io/PrintStream:println	(Ljava/lang/String;)V
    //   166: getstatic 37	java/lang/System:out	Ljava/io/PrintStream;
    //   169: aload_1
    //   170: invokestatic 69	weibo4android/org/json/JSONML:toString	(Lweibo4android/org/json/JSONObject;)Ljava/lang/String;
    //   173: invokevirtual 49	java/io/PrintStream:println	(Ljava/lang/String;)V
    //   176: getstatic 37	java/lang/System:out	Ljava/io/PrintStream;
    //   179: invokevirtual 63	java/io/PrintStream:println	()V
    //   182: ldc 81
    //   184: invokestatic 73	weibo4android/org/json/JSONML:toJSONArray	(Ljava/lang/String;)Lweibo4android/org/json/JSONArray;
    //   187: astore_1
    //   188: getstatic 37	java/lang/System:out	Ljava/io/PrintStream;
    //   191: aload_1
    //   192: iconst_4
    //   193: invokevirtual 76	weibo4android/org/json/JSONArray:toString	(I)Ljava/lang/String;
    //   196: invokevirtual 49	java/io/PrintStream:println	(Ljava/lang/String;)V
    //   199: getstatic 37	java/lang/System:out	Ljava/io/PrintStream;
    //   202: aload_1
    //   203: invokestatic 79	weibo4android/org/json/JSONML:toString	(Lweibo4android/org/json/JSONArray;)Ljava/lang/String;
    //   206: invokevirtual 49	java/io/PrintStream:println	(Ljava/lang/String;)V
    //   209: getstatic 37	java/lang/System:out	Ljava/io/PrintStream;
    //   212: invokevirtual 63	java/io/PrintStream:println	()V
    //   215: ldc 83
    //   217: invokestatic 31	weibo4android/org/json/XML:toJSONObject	(Ljava/lang/String;)Lweibo4android/org/json/JSONObject;
    //   220: astore_1
    //   221: getstatic 37	java/lang/System:out	Ljava/io/PrintStream;
    //   224: aload_1
    //   225: iconst_4
    //   226: invokevirtual 56	weibo4android/org/json/JSONObject:toString	(I)Ljava/lang/String;
    //   229: invokevirtual 49	java/io/PrintStream:println	(Ljava/lang/String;)V
    //   232: new 39	weibo4android/org/json/JSONObject
    //   235: dup
    //   236: aload_0
    //   237: invokespecial 86	weibo4android/org/json/JSONObject:<init>	(Ljava/lang/Object;)V
    //   240: astore_1
    //   241: getstatic 37	java/lang/System:out	Ljava/io/PrintStream;
    //   244: aload_1
    //   245: invokevirtual 43	weibo4android/org/json/JSONObject:toString	()Ljava/lang/String;
    //   248: invokevirtual 49	java/io/PrintStream:println	(Ljava/lang/String;)V
    //   251: new 39	weibo4android/org/json/JSONObject
    //   254: dup
    //   255: ldc 88
    //   257: invokespecial 53	weibo4android/org/json/JSONObject:<init>	(Ljava/lang/String;)V
    //   260: astore_1
    //   261: getstatic 37	java/lang/System:out	Ljava/io/PrintStream;
    //   264: aload_1
    //   265: iconst_2
    //   266: invokevirtual 56	weibo4android/org/json/JSONObject:toString	(I)Ljava/lang/String;
    //   269: invokevirtual 49	java/io/PrintStream:println	(Ljava/lang/String;)V
    //   272: new 90	weibo4android/org/json/JSONStringer
    //   275: dup
    //   276: invokespecial 91	weibo4android/org/json/JSONStringer:<init>	()V
    //   279: invokevirtual 95	weibo4android/org/json/JSONStringer:object	()Lweibo4android/org/json/JSONWriter;
    //   282: ldc 97
    //   284: invokevirtual 103	weibo4android/org/json/JSONWriter:key	(Ljava/lang/String;)Lweibo4android/org/json/JSONWriter;
    //   287: ldc 105
    //   289: invokevirtual 109	weibo4android/org/json/JSONWriter:value	(Ljava/lang/Object;)Lweibo4android/org/json/JSONWriter;
    //   292: ldc 111
    //   294: invokevirtual 103	weibo4android/org/json/JSONWriter:key	(Ljava/lang/String;)Lweibo4android/org/json/JSONWriter;
    //   297: ldc 113
    //   299: invokevirtual 109	weibo4android/org/json/JSONWriter:value	(Ljava/lang/Object;)Lweibo4android/org/json/JSONWriter;
    //   302: ldc 115
    //   304: invokevirtual 103	weibo4android/org/json/JSONWriter:key	(Ljava/lang/String;)Lweibo4android/org/json/JSONWriter;
    //   307: ldc 117
    //   309: invokevirtual 109	weibo4android/org/json/JSONWriter:value	(Ljava/lang/Object;)Lweibo4android/org/json/JSONWriter;
    //   312: ldc 119
    //   314: invokevirtual 103	weibo4android/org/json/JSONWriter:key	(Ljava/lang/String;)Lweibo4android/org/json/JSONWriter;
    //   317: invokevirtual 122	weibo4android/org/json/JSONWriter:array	()Lweibo4android/org/json/JSONWriter;
    //   320: invokevirtual 123	weibo4android/org/json/JSONWriter:object	()Lweibo4android/org/json/JSONWriter;
    //   323: ldc 125
    //   325: invokevirtual 103	weibo4android/org/json/JSONWriter:key	(Ljava/lang/String;)Lweibo4android/org/json/JSONWriter;
    //   328: ldc 127
    //   330: invokevirtual 109	weibo4android/org/json/JSONWriter:value	(Ljava/lang/Object;)Lweibo4android/org/json/JSONWriter;
    //   333: invokevirtual 130	weibo4android/org/json/JSONWriter:endObject	()Lweibo4android/org/json/JSONWriter;
    //   336: invokevirtual 133	weibo4android/org/json/JSONWriter:endArray	()Lweibo4android/org/json/JSONWriter;
    //   339: ldc 135
    //   341: invokevirtual 103	weibo4android/org/json/JSONWriter:key	(Ljava/lang/String;)Lweibo4android/org/json/JSONWriter;
    //   344: aload_0
    //   345: invokestatic 139	weibo4android/org/json/JSONObject:getNames	(Ljava/lang/Object;)[Ljava/lang/String;
    //   348: invokevirtual 109	weibo4android/org/json/JSONWriter:value	(Ljava/lang/Object;)Lweibo4android/org/json/JSONWriter;
    //   351: invokevirtual 130	weibo4android/org/json/JSONWriter:endObject	()Lweibo4android/org/json/JSONWriter;
    //   354: invokevirtual 140	java/lang/Object:toString	()Ljava/lang/String;
    //   357: astore_1
    //   358: getstatic 37	java/lang/System:out	Ljava/io/PrintStream;
    //   361: aload_1
    //   362: invokevirtual 49	java/io/PrintStream:println	(Ljava/lang/String;)V
    //   365: getstatic 37	java/lang/System:out	Ljava/io/PrintStream;
    //   368: new 90	weibo4android/org/json/JSONStringer
    //   371: dup
    //   372: invokespecial 91	weibo4android/org/json/JSONStringer:<init>	()V
    //   375: invokevirtual 95	weibo4android/org/json/JSONStringer:object	()Lweibo4android/org/json/JSONWriter;
    //   378: ldc 142
    //   380: invokevirtual 103	weibo4android/org/json/JSONWriter:key	(Ljava/lang/String;)Lweibo4android/org/json/JSONWriter;
    //   383: invokevirtual 122	weibo4android/org/json/JSONWriter:array	()Lweibo4android/org/json/JSONWriter;
    //   386: invokevirtual 122	weibo4android/org/json/JSONWriter:array	()Lweibo4android/org/json/JSONWriter;
    //   389: invokevirtual 122	weibo4android/org/json/JSONWriter:array	()Lweibo4android/org/json/JSONWriter;
    //   392: ldc 144
    //   394: invokevirtual 109	weibo4android/org/json/JSONWriter:value	(Ljava/lang/Object;)Lweibo4android/org/json/JSONWriter;
    //   397: invokevirtual 133	weibo4android/org/json/JSONWriter:endArray	()Lweibo4android/org/json/JSONWriter;
    //   400: invokevirtual 133	weibo4android/org/json/JSONWriter:endArray	()Lweibo4android/org/json/JSONWriter;
    //   403: invokevirtual 133	weibo4android/org/json/JSONWriter:endArray	()Lweibo4android/org/json/JSONWriter;
    //   406: invokevirtual 130	weibo4android/org/json/JSONWriter:endObject	()Lweibo4android/org/json/JSONWriter;
    //   409: invokevirtual 140	java/lang/Object:toString	()Ljava/lang/String;
    //   412: invokevirtual 49	java/io/PrintStream:println	(Ljava/lang/String;)V
    //   415: new 90	weibo4android/org/json/JSONStringer
    //   418: dup
    //   419: invokespecial 91	weibo4android/org/json/JSONStringer:<init>	()V
    //   422: astore_1
    //   423: aload_1
    //   424: invokevirtual 145	weibo4android/org/json/JSONStringer:array	()Lweibo4android/org/json/JSONWriter;
    //   427: pop
    //   428: aload_1
    //   429: lconst_1
    //   430: invokevirtual 148	weibo4android/org/json/JSONStringer:value	(J)Lweibo4android/org/json/JSONWriter;
    //   433: pop
    //   434: aload_1
    //   435: invokevirtual 145	weibo4android/org/json/JSONStringer:array	()Lweibo4android/org/json/JSONWriter;
    //   438: pop
    //   439: aload_1
    //   440: aconst_null
    //   441: invokevirtual 149	weibo4android/org/json/JSONStringer:value	(Ljava/lang/Object;)Lweibo4android/org/json/JSONWriter;
    //   444: pop
    //   445: aload_1
    //   446: invokevirtual 145	weibo4android/org/json/JSONStringer:array	()Lweibo4android/org/json/JSONWriter;
    //   449: pop
    //   450: aload_1
    //   451: invokevirtual 95	weibo4android/org/json/JSONStringer:object	()Lweibo4android/org/json/JSONWriter;
    //   454: pop
    //   455: aload_1
    //   456: ldc 151
    //   458: invokevirtual 152	weibo4android/org/json/JSONStringer:key	(Ljava/lang/String;)Lweibo4android/org/json/JSONWriter;
    //   461: invokevirtual 122	weibo4android/org/json/JSONWriter:array	()Lweibo4android/org/json/JSONWriter;
    //   464: invokevirtual 133	weibo4android/org/json/JSONWriter:endArray	()Lweibo4android/org/json/JSONWriter;
    //   467: pop
    //   468: aload_1
    //   469: ldc 154
    //   471: invokevirtual 152	weibo4android/org/json/JSONStringer:key	(Ljava/lang/String;)Lweibo4android/org/json/JSONWriter;
    //   474: ldc2_w 155
    //   477: invokevirtual 157	weibo4android/org/json/JSONWriter:value	(J)Lweibo4android/org/json/JSONWriter;
    //   480: pop
    //   481: aload_1
    //   482: ldc 159
    //   484: invokevirtual 152	weibo4android/org/json/JSONStringer:key	(Ljava/lang/String;)Lweibo4android/org/json/JSONWriter;
    //   487: aconst_null
    //   488: invokevirtual 109	weibo4android/org/json/JSONWriter:value	(Ljava/lang/Object;)Lweibo4android/org/json/JSONWriter;
    //   491: pop
    //   492: aload_1
    //   493: ldc 161
    //   495: invokevirtual 152	weibo4android/org/json/JSONStringer:key	(Ljava/lang/String;)Lweibo4android/org/json/JSONWriter;
    //   498: iconst_0
    //   499: invokevirtual 164	weibo4android/org/json/JSONWriter:value	(Z)Lweibo4android/org/json/JSONWriter;
    //   502: pop
    //   503: aload_1
    //   504: ldc 166
    //   506: invokevirtual 152	weibo4android/org/json/JSONStringer:key	(Ljava/lang/String;)Lweibo4android/org/json/JSONWriter;
    //   509: iconst_1
    //   510: invokevirtual 164	weibo4android/org/json/JSONWriter:value	(Z)Lweibo4android/org/json/JSONWriter;
    //   513: pop
    //   514: aload_1
    //   515: ldc 168
    //   517: invokevirtual 152	weibo4android/org/json/JSONStringer:key	(Ljava/lang/String;)Lweibo4android/org/json/JSONWriter;
    //   520: ldc2_w 169
    //   523: invokevirtual 173	weibo4android/org/json/JSONWriter:value	(D)Lweibo4android/org/json/JSONWriter;
    //   526: pop
    //   527: aload_1
    //   528: ldc 175
    //   530: invokevirtual 152	weibo4android/org/json/JSONStringer:key	(Ljava/lang/String;)Lweibo4android/org/json/JSONWriter;
    //   533: ldc2_w 176
    //   536: invokevirtual 173	weibo4android/org/json/JSONWriter:value	(D)Lweibo4android/org/json/JSONWriter;
    //   539: pop
    //   540: aload_1
    //   541: ldc 179
    //   543: invokevirtual 152	weibo4android/org/json/JSONStringer:key	(Ljava/lang/String;)Lweibo4android/org/json/JSONWriter;
    //   546: invokevirtual 123	weibo4android/org/json/JSONWriter:object	()Lweibo4android/org/json/JSONWriter;
    //   549: invokevirtual 130	weibo4android/org/json/JSONWriter:endObject	()Lweibo4android/org/json/JSONWriter;
    //   552: pop
    //   553: aload_1
    //   554: ldc 181
    //   556: invokevirtual 152	weibo4android/org/json/JSONStringer:key	(Ljava/lang/String;)Lweibo4android/org/json/JSONWriter;
    //   559: pop
    //   560: aload_1
    //   561: ldc2_w 182
    //   564: invokevirtual 148	weibo4android/org/json/JSONStringer:value	(J)Lweibo4android/org/json/JSONWriter;
    //   567: pop
    //   568: aload_1
    //   569: invokevirtual 184	weibo4android/org/json/JSONStringer:endObject	()Lweibo4android/org/json/JSONWriter;
    //   572: pop
    //   573: aload_1
    //   574: ldc 186
    //   576: invokevirtual 149	weibo4android/org/json/JSONStringer:value	(Ljava/lang/Object;)Lweibo4android/org/json/JSONWriter;
    //   579: pop
    //   580: aload_1
    //   581: invokevirtual 187	weibo4android/org/json/JSONStringer:endArray	()Lweibo4android/org/json/JSONWriter;
    //   584: pop
    //   585: aload_1
    //   586: iconst_1
    //   587: invokevirtual 188	weibo4android/org/json/JSONStringer:value	(Z)Lweibo4android/org/json/JSONWriter;
    //   590: pop
    //   591: aload_1
    //   592: invokevirtual 187	weibo4android/org/json/JSONStringer:endArray	()Lweibo4android/org/json/JSONWriter;
    //   595: pop
    //   596: aload_1
    //   597: ldc2_w 189
    //   600: invokevirtual 191	weibo4android/org/json/JSONStringer:value	(D)Lweibo4android/org/json/JSONWriter;
    //   603: pop
    //   604: aload_1
    //   605: ldc2_w 192
    //   608: invokevirtual 191	weibo4android/org/json/JSONStringer:value	(D)Lweibo4android/org/json/JSONWriter;
    //   611: pop
    //   612: aload_1
    //   613: invokevirtual 95	weibo4android/org/json/JSONStringer:object	()Lweibo4android/org/json/JSONWriter;
    //   616: pop
    //   617: aload_1
    //   618: invokevirtual 184	weibo4android/org/json/JSONStringer:endObject	()Lweibo4android/org/json/JSONWriter;
    //   621: pop
    //   622: aload_1
    //   623: invokevirtual 95	weibo4android/org/json/JSONStringer:object	()Lweibo4android/org/json/JSONWriter;
    //   626: pop
    //   627: aload_1
    //   628: ldc 195
    //   630: invokevirtual 152	weibo4android/org/json/JSONStringer:key	(Ljava/lang/String;)Lweibo4android/org/json/JSONWriter;
    //   633: pop
    //   634: aload_1
    //   635: dconst_1
    //   636: invokevirtual 191	weibo4android/org/json/JSONStringer:value	(D)Lweibo4android/org/json/JSONWriter;
    //   639: pop
    //   640: aload_1
    //   641: invokevirtual 184	weibo4android/org/json/JSONStringer:endObject	()Lweibo4android/org/json/JSONWriter;
    //   644: pop
    //   645: aload_1
    //   646: aload_0
    //   647: invokevirtual 149	weibo4android/org/json/JSONStringer:value	(Ljava/lang/Object;)Lweibo4android/org/json/JSONWriter;
    //   650: pop
    //   651: aload_1
    //   652: invokevirtual 187	weibo4android/org/json/JSONStringer:endArray	()Lweibo4android/org/json/JSONWriter;
    //   655: pop
    //   656: getstatic 37	java/lang/System:out	Ljava/io/PrintStream;
    //   659: aload_1
    //   660: invokevirtual 196	weibo4android/org/json/JSONStringer:toString	()Ljava/lang/String;
    //   663: invokevirtual 49	java/io/PrintStream:println	(Ljava/lang/String;)V
    //   666: getstatic 37	java/lang/System:out	Ljava/io/PrintStream;
    //   669: new 75	weibo4android/org/json/JSONArray
    //   672: dup
    //   673: aload_1
    //   674: invokevirtual 196	weibo4android/org/json/JSONStringer:toString	()Ljava/lang/String;
    //   677: invokespecial 197	weibo4android/org/json/JSONArray:<init>	(Ljava/lang/String;)V
    //   680: iconst_4
    //   681: invokevirtual 76	weibo4android/org/json/JSONArray:toString	(I)Ljava/lang/String;
    //   684: invokevirtual 49	java/io/PrintStream:println	(Ljava/lang/String;)V
    //   687: new 75	weibo4android/org/json/JSONArray
    //   690: dup
    //   691: iconst_3
    //   692: newarray int
    //   694: dup
    //   695: iconst_0
    //   696: iconst_1
    //   697: iastore
    //   698: dup
    //   699: iconst_1
    //   700: iconst_2
    //   701: iastore
    //   702: dup
    //   703: iconst_2
    //   704: iconst_3
    //   705: iastore
    //   706: invokespecial 198	weibo4android/org/json/JSONArray:<init>	(Ljava/lang/Object;)V
    //   709: astore_1
    //   710: getstatic 37	java/lang/System:out	Ljava/io/PrintStream;
    //   713: aload_1
    //   714: invokevirtual 199	weibo4android/org/json/JSONArray:toString	()Ljava/lang/String;
    //   717: invokevirtual 49	java/io/PrintStream:println	(Ljava/lang/String;)V
    //   720: new 39	weibo4android/org/json/JSONObject
    //   723: dup
    //   724: aload_0
    //   725: iconst_3
    //   726: anewarray 201	java/lang/String
    //   729: dup
    //   730: iconst_0
    //   731: ldc 203
    //   733: aastore
    //   734: dup
    //   735: iconst_1
    //   736: ldc 205
    //   738: aastore
    //   739: dup
    //   740: iconst_2
    //   741: ldc 207
    //   743: aastore
    //   744: invokespecial 210	weibo4android/org/json/JSONObject:<init>	(Ljava/lang/Object;[Ljava/lang/String;)V
    //   747: astore_1
    //   748: aload_1
    //   749: ldc 212
    //   751: aload_0
    //   752: invokevirtual 216	weibo4android/org/json/JSONObject:put	(Ljava/lang/String;Ljava/lang/Object;)Lweibo4android/org/json/JSONObject;
    //   755: pop
    //   756: getstatic 37	java/lang/System:out	Ljava/io/PrintStream;
    //   759: aload_1
    //   760: iconst_4
    //   761: invokevirtual 56	weibo4android/org/json/JSONObject:toString	(I)Ljava/lang/String;
    //   764: invokevirtual 49	java/io/PrintStream:println	(Ljava/lang/String;)V
    //   767: new 39	weibo4android/org/json/JSONObject
    //   770: dup
    //   771: ldc 218
    //   773: invokespecial 53	weibo4android/org/json/JSONObject:<init>	(Ljava/lang/String;)V
    //   776: astore_0
    //   777: getstatic 37	java/lang/System:out	Ljava/io/PrintStream;
    //   780: aload_0
    //   781: iconst_2
    //   782: invokevirtual 56	weibo4android/org/json/JSONObject:toString	(I)Ljava/lang/String;
    //   785: invokevirtual 49	java/io/PrintStream:println	(Ljava/lang/String;)V
    //   788: getstatic 37	java/lang/System:out	Ljava/io/PrintStream;
    //   791: aload_0
    //   792: invokestatic 59	weibo4android/org/json/XML:toString	(Ljava/lang/Object;)Ljava/lang/String;
    //   795: invokevirtual 49	java/io/PrintStream:println	(Ljava/lang/String;)V
    //   798: getstatic 37	java/lang/System:out	Ljava/io/PrintStream;
    //   801: ldc 220
    //   803: invokevirtual 49	java/io/PrintStream:println	(Ljava/lang/String;)V
    //   806: new 39	weibo4android/org/json/JSONObject
    //   809: dup
    //   810: ldc 222
    //   812: invokespecial 53	weibo4android/org/json/JSONObject:<init>	(Ljava/lang/String;)V
    //   815: astore_0
    //   816: aload_0
    //   817: ldc 224
    //   819: ldc 226
    //   821: invokevirtual 216	weibo4android/org/json/JSONObject:put	(Ljava/lang/String;Ljava/lang/Object;)Lweibo4android/org/json/JSONObject;
    //   824: pop
    //   825: aload_0
    //   826: ldc 228
    //   828: new 39	weibo4android/org/json/JSONObject
    //   831: dup
    //   832: invokespecial 229	weibo4android/org/json/JSONObject:<init>	()V
    //   835: invokevirtual 216	weibo4android/org/json/JSONObject:put	(Ljava/lang/String;Ljava/lang/Object;)Lweibo4android/org/json/JSONObject;
    //   838: pop
    //   839: aload_0
    //   840: ldc 231
    //   842: new 75	weibo4android/org/json/JSONArray
    //   845: dup
    //   846: invokespecial 232	weibo4android/org/json/JSONArray:<init>	()V
    //   849: invokevirtual 216	weibo4android/org/json/JSONObject:put	(Ljava/lang/String;Ljava/lang/Object;)Lweibo4android/org/json/JSONObject;
    //   852: pop
    //   853: aload_0
    //   854: ldc 234
    //   856: bipush 57
    //   858: invokevirtual 237	weibo4android/org/json/JSONObject:put	(Ljava/lang/String;I)Lweibo4android/org/json/JSONObject;
    //   861: pop
    //   862: aload_0
    //   863: ldc 239
    //   865: ldc2_w 240
    //   868: invokevirtual 244	weibo4android/org/json/JSONObject:put	(Ljava/lang/String;D)Lweibo4android/org/json/JSONObject;
    //   871: pop
    //   872: aload_0
    //   873: ldc 166
    //   875: iconst_1
    //   876: invokevirtual 247	weibo4android/org/json/JSONObject:put	(Ljava/lang/String;Z)Lweibo4android/org/json/JSONObject;
    //   879: pop
    //   880: aload_0
    //   881: ldc 161
    //   883: iconst_0
    //   884: invokevirtual 247	weibo4android/org/json/JSONObject:put	(Ljava/lang/String;Z)Lweibo4android/org/json/JSONObject;
    //   887: pop
    //   888: aload_0
    //   889: ldc 159
    //   891: getstatic 251	weibo4android/org/json/JSONObject:NULL	Ljava/lang/Object;
    //   894: invokevirtual 216	weibo4android/org/json/JSONObject:put	(Ljava/lang/String;Ljava/lang/Object;)Lweibo4android/org/json/JSONObject;
    //   897: pop
    //   898: aload_0
    //   899: ldc 253
    //   901: ldc 166
    //   903: invokevirtual 216	weibo4android/org/json/JSONObject:put	(Ljava/lang/String;Ljava/lang/Object;)Lweibo4android/org/json/JSONObject;
    //   906: pop
    //   907: aload_0
    //   908: ldc 255
    //   910: dconst_0
    //   911: invokevirtual 244	weibo4android/org/json/JSONObject:put	(Ljava/lang/String;D)Lweibo4android/org/json/JSONObject;
    //   914: pop
    //   915: aload_0
    //   916: ldc_w 257
    //   919: ldc_w 259
    //   922: invokevirtual 216	weibo4android/org/json/JSONObject:put	(Ljava/lang/String;Ljava/lang/Object;)Lweibo4android/org/json/JSONObject;
    //   925: pop
    //   926: aload_0
    //   927: ldc_w 261
    //   930: ldc_w 263
    //   933: invokevirtual 216	weibo4android/org/json/JSONObject:put	(Ljava/lang/String;Ljava/lang/Object;)Lweibo4android/org/json/JSONObject;
    //   936: pop
    //   937: aload_0
    //   938: ldc 115
    //   940: invokevirtual 266	weibo4android/org/json/JSONObject:getJSONArray	(Ljava/lang/String;)Lweibo4android/org/json/JSONArray;
    //   943: astore_1
    //   944: aload_1
    //   945: sipush 666
    //   948: invokevirtual 269	weibo4android/org/json/JSONArray:put	(I)Lweibo4android/org/json/JSONArray;
    //   951: pop
    //   952: aload_1
    //   953: ldc2_w 270
    //   956: invokevirtual 274	weibo4android/org/json/JSONArray:put	(D)Lweibo4android/org/json/JSONArray;
    //   959: pop
    //   960: aload_1
    //   961: ldc_w 276
    //   964: invokevirtual 279	weibo4android/org/json/JSONArray:put	(Ljava/lang/Object;)Lweibo4android/org/json/JSONArray;
    //   967: pop
    //   968: aload_1
    //   969: ldc_w 281
    //   972: invokevirtual 279	weibo4android/org/json/JSONArray:put	(Ljava/lang/Object;)Lweibo4android/org/json/JSONArray;
    //   975: pop
    //   976: aload_1
    //   977: iconst_1
    //   978: invokevirtual 284	weibo4android/org/json/JSONArray:put	(Z)Lweibo4android/org/json/JSONArray;
    //   981: pop
    //   982: aload_1
    //   983: iconst_0
    //   984: invokevirtual 284	weibo4android/org/json/JSONArray:put	(Z)Lweibo4android/org/json/JSONArray;
    //   987: pop
    //   988: aload_1
    //   989: new 75	weibo4android/org/json/JSONArray
    //   992: dup
    //   993: invokespecial 232	weibo4android/org/json/JSONArray:<init>	()V
    //   996: invokevirtual 279	weibo4android/org/json/JSONArray:put	(Ljava/lang/Object;)Lweibo4android/org/json/JSONArray;
    //   999: pop
    //   1000: aload_1
    //   1001: new 39	weibo4android/org/json/JSONObject
    //   1004: dup
    //   1005: invokespecial 229	weibo4android/org/json/JSONObject:<init>	()V
    //   1008: invokevirtual 279	weibo4android/org/json/JSONArray:put	(Ljava/lang/Object;)Lweibo4android/org/json/JSONArray;
    //   1011: pop
    //   1012: aload_0
    //   1013: ldc_w 286
    //   1016: aload_0
    //   1017: invokestatic 289	weibo4android/org/json/JSONObject:getNames	(Lweibo4android/org/json/JSONObject;)[Ljava/lang/String;
    //   1020: invokevirtual 216	weibo4android/org/json/JSONObject:put	(Ljava/lang/String;Ljava/lang/Object;)Lweibo4android/org/json/JSONObject;
    //   1023: pop
    //   1024: getstatic 37	java/lang/System:out	Ljava/io/PrintStream;
    //   1027: aload_0
    //   1028: iconst_4
    //   1029: invokevirtual 56	weibo4android/org/json/JSONObject:toString	(I)Ljava/lang/String;
    //   1032: invokevirtual 49	java/io/PrintStream:println	(Ljava/lang/String;)V
    //   1035: getstatic 37	java/lang/System:out	Ljava/io/PrintStream;
    //   1038: aload_0
    //   1039: invokestatic 59	weibo4android/org/json/XML:toString	(Ljava/lang/Object;)Ljava/lang/String;
    //   1042: invokevirtual 49	java/io/PrintStream:println	(Ljava/lang/String;)V
    //   1045: getstatic 37	java/lang/System:out	Ljava/io/PrintStream;
    //   1048: new 291	java/lang/StringBuilder
    //   1051: dup
    //   1052: invokespecial 292	java/lang/StringBuilder:<init>	()V
    //   1055: ldc_w 294
    //   1058: invokevirtual 298	java/lang/StringBuilder:append	(Ljava/lang/String;)Ljava/lang/StringBuilder;
    //   1061: aload_0
    //   1062: ldc 224
    //   1064: invokevirtual 302	weibo4android/org/json/JSONObject:getDouble	(Ljava/lang/String;)D
    //   1067: invokevirtual 305	java/lang/StringBuilder:append	(D)Ljava/lang/StringBuilder;
    //   1070: invokevirtual 306	java/lang/StringBuilder:toString	()Ljava/lang/String;
    //   1073: invokevirtual 49	java/io/PrintStream:println	(Ljava/lang/String;)V
    //   1076: getstatic 37	java/lang/System:out	Ljava/io/PrintStream;
    //   1079: new 291	java/lang/StringBuilder
    //   1082: dup
    //   1083: invokespecial 292	java/lang/StringBuilder:<init>	()V
    //   1086: ldc_w 308
    //   1089: invokevirtual 298	java/lang/StringBuilder:append	(Ljava/lang/String;)Ljava/lang/StringBuilder;
    //   1092: aload_0
    //   1093: ldc 253
    //   1095: invokevirtual 312	weibo4android/org/json/JSONObject:getBoolean	(Ljava/lang/String;)Z
    //   1098: invokevirtual 315	java/lang/StringBuilder:append	(Z)Ljava/lang/StringBuilder;
    //   1101: invokevirtual 306	java/lang/StringBuilder:toString	()Ljava/lang/String;
    //   1104: invokevirtual 49	java/io/PrintStream:println	(Ljava/lang/String;)V
    //   1107: getstatic 37	java/lang/System:out	Ljava/io/PrintStream;
    //   1110: new 291	java/lang/StringBuilder
    //   1113: dup
    //   1114: invokespecial 292	java/lang/StringBuilder:<init>	()V
    //   1117: ldc_w 317
    //   1120: invokevirtual 298	java/lang/StringBuilder:append	(Ljava/lang/String;)Ljava/lang/StringBuilder;
    //   1123: aload_0
    //   1124: ldc_w 319
    //   1127: invokevirtual 323	weibo4android/org/json/JSONObject:getString	(Ljava/lang/String;)Ljava/lang/String;
    //   1130: invokevirtual 298	java/lang/StringBuilder:append	(Ljava/lang/String;)Ljava/lang/StringBuilder;
    //   1133: invokevirtual 306	java/lang/StringBuilder:toString	()Ljava/lang/String;
    //   1136: invokevirtual 49	java/io/PrintStream:println	(Ljava/lang/String;)V
    //   1139: getstatic 37	java/lang/System:out	Ljava/io/PrintStream;
    //   1142: new 291	java/lang/StringBuilder
    //   1145: dup
    //   1146: invokespecial 292	java/lang/StringBuilder:<init>	()V
    //   1149: ldc_w 325
    //   1152: invokevirtual 298	java/lang/StringBuilder:append	(Ljava/lang/String;)Ljava/lang/StringBuilder;
    //   1155: aload_0
    //   1156: ldc 166
    //   1158: invokevirtual 323	weibo4android/org/json/JSONObject:getString	(Ljava/lang/String;)Ljava/lang/String;
    //   1161: invokevirtual 298	java/lang/StringBuilder:append	(Ljava/lang/String;)Ljava/lang/StringBuilder;
    //   1164: invokevirtual 306	java/lang/StringBuilder:toString	()Ljava/lang/String;
    //   1167: invokevirtual 49	java/io/PrintStream:println	(Ljava/lang/String;)V
    //   1170: getstatic 37	java/lang/System:out	Ljava/io/PrintStream;
    //   1173: new 291	java/lang/StringBuilder
    //   1176: dup
    //   1177: invokespecial 292	java/lang/StringBuilder:<init>	()V
    //   1180: ldc_w 327
    //   1183: invokevirtual 298	java/lang/StringBuilder:append	(Ljava/lang/String;)Ljava/lang/StringBuilder;
    //   1186: aload_0
    //   1187: ldc 115
    //   1189: invokevirtual 266	weibo4android/org/json/JSONObject:getJSONArray	(Ljava/lang/String;)Lweibo4android/org/json/JSONArray;
    //   1192: invokevirtual 330	java/lang/StringBuilder:append	(Ljava/lang/Object;)Ljava/lang/StringBuilder;
    //   1195: invokevirtual 306	java/lang/StringBuilder:toString	()Ljava/lang/String;
    //   1198: invokevirtual 49	java/io/PrintStream:println	(Ljava/lang/String;)V
    //   1201: getstatic 37	java/lang/System:out	Ljava/io/PrintStream;
    //   1204: new 291	java/lang/StringBuilder
    //   1207: dup
    //   1208: invokespecial 292	java/lang/StringBuilder:<init>	()V
    //   1211: ldc_w 332
    //   1214: invokevirtual 298	java/lang/StringBuilder:append	(Ljava/lang/String;)Ljava/lang/StringBuilder;
    //   1217: aload_0
    //   1218: ldc_w 334
    //   1221: invokevirtual 323	weibo4android/org/json/JSONObject:getString	(Ljava/lang/String;)Ljava/lang/String;
    //   1224: invokevirtual 298	java/lang/StringBuilder:append	(Ljava/lang/String;)Ljava/lang/StringBuilder;
    //   1227: invokevirtual 306	java/lang/StringBuilder:toString	()Ljava/lang/String;
    //   1230: invokevirtual 49	java/io/PrintStream:println	(Ljava/lang/String;)V
    //   1233: getstatic 37	java/lang/System:out	Ljava/io/PrintStream;
    //   1236: new 291	java/lang/StringBuilder
    //   1239: dup
    //   1240: invokespecial 292	java/lang/StringBuilder:<init>	()V
    //   1243: ldc_w 336
    //   1246: invokevirtual 298	java/lang/StringBuilder:append	(Ljava/lang/String;)Ljava/lang/StringBuilder;
    //   1249: aload_0
    //   1250: ldc_w 338
    //   1253: invokevirtual 342	weibo4android/org/json/JSONObject:getInt	(Ljava/lang/String;)I
    //   1256: invokevirtual 345	java/lang/StringBuilder:append	(I)Ljava/lang/StringBuilder;
    //   1259: invokevirtual 306	java/lang/StringBuilder:toString	()Ljava/lang/String;
    //   1262: invokevirtual 49	java/io/PrintStream:println	(Ljava/lang/String;)V
    //   1265: getstatic 37	java/lang/System:out	Ljava/io/PrintStream;
    //   1268: new 291	java/lang/StringBuilder
    //   1271: dup
    //   1272: invokespecial 292	java/lang/StringBuilder:<init>	()V
    //   1275: ldc_w 347
    //   1278: invokevirtual 298	java/lang/StringBuilder:append	(Ljava/lang/String;)Ljava/lang/StringBuilder;
    //   1281: aload_0
    //   1282: ldc_w 349
    //   1285: invokevirtual 352	weibo4android/org/json/JSONObject:optBoolean	(Ljava/lang/String;)Z
    //   1288: invokevirtual 315	java/lang/StringBuilder:append	(Z)Ljava/lang/StringBuilder;
    //   1291: invokevirtual 306	java/lang/StringBuilder:toString	()Ljava/lang/String;
    //   1294: invokevirtual 49	java/io/PrintStream:println	(Ljava/lang/String;)V
    //   1297: ldc_w 354
    //   1300: invokestatic 31	weibo4android/org/json/XML:toJSONObject	(Ljava/lang/String;)Lweibo4android/org/json/JSONObject;
    //   1303: astore_0
    //   1304: getstatic 37	java/lang/System:out	Ljava/io/PrintStream;
    //   1307: aload_0
    //   1308: iconst_2
    //   1309: invokevirtual 56	weibo4android/org/json/JSONObject:toString	(I)Ljava/lang/String;
    //   1312: invokevirtual 49	java/io/PrintStream:println	(Ljava/lang/String;)V
    //   1315: getstatic 37	java/lang/System:out	Ljava/io/PrintStream;
    //   1318: aload_0
    //   1319: invokestatic 59	weibo4android/org/json/XML:toString	(Ljava/lang/Object;)Ljava/lang/String;
    //   1322: invokevirtual 49	java/io/PrintStream:println	(Ljava/lang/String;)V
    //   1325: getstatic 37	java/lang/System:out	Ljava/io/PrintStream;
    //   1328: ldc 220
    //   1330: invokevirtual 49	java/io/PrintStream:println	(Ljava/lang/String;)V
    //   1333: ldc_w 354
    //   1336: invokestatic 73	weibo4android/org/json/JSONML:toJSONArray	(Ljava/lang/String;)Lweibo4android/org/json/JSONArray;
    //   1339: astore_0
    //   1340: getstatic 37	java/lang/System:out	Ljava/io/PrintStream;
    //   1343: aload_0
    //   1344: iconst_4
    //   1345: invokevirtual 76	weibo4android/org/json/JSONArray:toString	(I)Ljava/lang/String;
    //   1348: invokevirtual 49	java/io/PrintStream:println	(Ljava/lang/String;)V
    //   1351: getstatic 37	java/lang/System:out	Ljava/io/PrintStream;
    //   1354: aload_0
    //   1355: invokestatic 79	weibo4android/org/json/JSONML:toString	(Lweibo4android/org/json/JSONArray;)Ljava/lang/String;
    //   1358: invokevirtual 49	java/io/PrintStream:println	(Ljava/lang/String;)V
    //   1361: getstatic 37	java/lang/System:out	Ljava/io/PrintStream;
    //   1364: ldc 220
    //   1366: invokevirtual 49	java/io/PrintStream:println	(Ljava/lang/String;)V
    //   1369: ldc_w 356
    //   1372: invokestatic 73	weibo4android/org/json/JSONML:toJSONArray	(Ljava/lang/String;)Lweibo4android/org/json/JSONArray;
    //   1375: astore_0
    //   1376: getstatic 37	java/lang/System:out	Ljava/io/PrintStream;
    //   1379: aload_0
    //   1380: iconst_4
    //   1381: invokevirtual 76	weibo4android/org/json/JSONArray:toString	(I)Ljava/lang/String;
    //   1384: invokevirtual 49	java/io/PrintStream:println	(Ljava/lang/String;)V
    //   1387: getstatic 37	java/lang/System:out	Ljava/io/PrintStream;
    //   1390: aload_0
    //   1391: invokestatic 79	weibo4android/org/json/JSONML:toString	(Lweibo4android/org/json/JSONArray;)Ljava/lang/String;
    //   1394: invokevirtual 49	java/io/PrintStream:println	(Ljava/lang/String;)V
    //   1397: getstatic 37	java/lang/System:out	Ljava/io/PrintStream;
    //   1400: ldc 220
    //   1402: invokevirtual 49	java/io/PrintStream:println	(Ljava/lang/String;)V
    //   1405: ldc_w 358
    //   1408: invokestatic 31	weibo4android/org/json/XML:toJSONObject	(Ljava/lang/String;)Lweibo4android/org/json/JSONObject;
    //   1411: astore_0
    //   1412: getstatic 37	java/lang/System:out	Ljava/io/PrintStream;
    //   1415: aload_0
    //   1416: iconst_2
    //   1417: invokevirtual 56	weibo4android/org/json/JSONObject:toString	(I)Ljava/lang/String;
    //   1420: invokevirtual 49	java/io/PrintStream:println	(Ljava/lang/String;)V
    //   1423: getstatic 37	java/lang/System:out	Ljava/io/PrintStream;
    //   1426: aload_0
    //   1427: invokestatic 59	weibo4android/org/json/XML:toString	(Ljava/lang/Object;)Ljava/lang/String;
    //   1430: invokevirtual 49	java/io/PrintStream:println	(Ljava/lang/String;)V
    //   1433: getstatic 37	java/lang/System:out	Ljava/io/PrintStream;
    //   1436: ldc 220
    //   1438: invokevirtual 49	java/io/PrintStream:println	(Ljava/lang/String;)V
    //   1441: ldc_w 358
    //   1444: invokestatic 73	weibo4android/org/json/JSONML:toJSONArray	(Ljava/lang/String;)Lweibo4android/org/json/JSONArray;
    //   1447: astore_0
    //   1448: getstatic 37	java/lang/System:out	Ljava/io/PrintStream;
    //   1451: aload_0
    //   1452: iconst_4
    //   1453: invokevirtual 76	weibo4android/org/json/JSONArray:toString	(I)Ljava/lang/String;
    //   1456: invokevirtual 49	java/io/PrintStream:println	(Ljava/lang/String;)V
    //   1459: getstatic 37	java/lang/System:out	Ljava/io/PrintStream;
    //   1462: aload_0
    //   1463: invokestatic 79	weibo4android/org/json/JSONML:toString	(Lweibo4android/org/json/JSONArray;)Ljava/lang/String;
    //   1466: invokevirtual 49	java/io/PrintStream:println	(Ljava/lang/String;)V
    //   1469: getstatic 37	java/lang/System:out	Ljava/io/PrintStream;
    //   1472: ldc 220
    //   1474: invokevirtual 49	java/io/PrintStream:println	(Ljava/lang/String;)V
    //   1477: ldc_w 360
    //   1480: invokestatic 31	weibo4android/org/json/XML:toJSONObject	(Ljava/lang/String;)Lweibo4android/org/json/JSONObject;
    //   1483: astore_0
    //   1484: getstatic 37	java/lang/System:out	Ljava/io/PrintStream;
    //   1487: aload_0
    //   1488: iconst_2
    //   1489: invokevirtual 56	weibo4android/org/json/JSONObject:toString	(I)Ljava/lang/String;
    //   1492: invokevirtual 49	java/io/PrintStream:println	(Ljava/lang/String;)V
    //   1495: getstatic 37	java/lang/System:out	Ljava/io/PrintStream;
    //   1498: aload_0
    //   1499: invokestatic 59	weibo4android/org/json/XML:toString	(Ljava/lang/Object;)Ljava/lang/String;
    //   1502: invokevirtual 49	java/io/PrintStream:println	(Ljava/lang/String;)V
    //   1505: getstatic 37	java/lang/System:out	Ljava/io/PrintStream;
    //   1508: ldc 220
    //   1510: invokevirtual 49	java/io/PrintStream:println	(Ljava/lang/String;)V
    //   1513: ldc_w 362
    //   1516: invokestatic 31	weibo4android/org/json/XML:toJSONObject	(Ljava/lang/String;)Lweibo4android/org/json/JSONObject;
    //   1519: astore_0
    //   1520: getstatic 37	java/lang/System:out	Ljava/io/PrintStream;
    //   1523: aload_0
    //   1524: iconst_2
    //   1525: invokevirtual 56	weibo4android/org/json/JSONObject:toString	(I)Ljava/lang/String;
    //   1528: invokevirtual 49	java/io/PrintStream:println	(Ljava/lang/String;)V
    //   1531: getstatic 37	java/lang/System:out	Ljava/io/PrintStream;
    //   1534: aload_0
    //   1535: invokestatic 59	weibo4android/org/json/XML:toString	(Ljava/lang/Object;)Ljava/lang/String;
    //   1538: invokevirtual 49	java/io/PrintStream:println	(Ljava/lang/String;)V
    //   1541: getstatic 37	java/lang/System:out	Ljava/io/PrintStream;
    //   1544: ldc 220
    //   1546: invokevirtual 49	java/io/PrintStream:println	(Ljava/lang/String;)V
    //   1549: ldc_w 364
    //   1552: invokestatic 31	weibo4android/org/json/XML:toJSONObject	(Ljava/lang/String;)Lweibo4android/org/json/JSONObject;
    //   1555: astore_0
    //   1556: getstatic 37	java/lang/System:out	Ljava/io/PrintStream;
    //   1559: aload_0
    //   1560: iconst_2
    //   1561: invokevirtual 56	weibo4android/org/json/JSONObject:toString	(I)Ljava/lang/String;
    //   1564: invokevirtual 49	java/io/PrintStream:println	(Ljava/lang/String;)V
    //   1567: getstatic 37	java/lang/System:out	Ljava/io/PrintStream;
    //   1570: aload_0
    //   1571: invokestatic 59	weibo4android/org/json/XML:toString	(Ljava/lang/Object;)Ljava/lang/String;
    //   1574: invokevirtual 49	java/io/PrintStream:println	(Ljava/lang/String;)V
    //   1577: getstatic 37	java/lang/System:out	Ljava/io/PrintStream;
    //   1580: ldc 220
    //   1582: invokevirtual 49	java/io/PrintStream:println	(Ljava/lang/String;)V
    //   1585: ldc_w 366
    //   1588: invokestatic 31	weibo4android/org/json/XML:toJSONObject	(Ljava/lang/String;)Lweibo4android/org/json/JSONObject;
    //   1591: astore_0
    //   1592: getstatic 37	java/lang/System:out	Ljava/io/PrintStream;
    //   1595: aload_0
    //   1596: invokevirtual 43	weibo4android/org/json/JSONObject:toString	()Ljava/lang/String;
    //   1599: invokevirtual 49	java/io/PrintStream:println	(Ljava/lang/String;)V
    //   1602: getstatic 37	java/lang/System:out	Ljava/io/PrintStream;
    //   1605: aload_0
    //   1606: invokestatic 59	weibo4android/org/json/XML:toString	(Ljava/lang/Object;)Ljava/lang/String;
    //   1609: invokevirtual 49	java/io/PrintStream:println	(Ljava/lang/String;)V
    //   1612: getstatic 37	java/lang/System:out	Ljava/io/PrintStream;
    //   1615: ldc 220
    //   1617: invokevirtual 49	java/io/PrintStream:println	(Ljava/lang/String;)V
    //   1620: ldc_w 368
    //   1623: invokestatic 31	weibo4android/org/json/XML:toJSONObject	(Ljava/lang/String;)Lweibo4android/org/json/JSONObject;
    //   1626: astore_0
    //   1627: getstatic 37	java/lang/System:out	Ljava/io/PrintStream;
    //   1630: aload_0
    //   1631: iconst_2
    //   1632: invokevirtual 56	weibo4android/org/json/JSONObject:toString	(I)Ljava/lang/String;
    //   1635: invokevirtual 49	java/io/PrintStream:println	(Ljava/lang/String;)V
    //   1638: getstatic 37	java/lang/System:out	Ljava/io/PrintStream;
    //   1641: aload_0
    //   1642: invokestatic 59	weibo4android/org/json/XML:toString	(Ljava/lang/Object;)Ljava/lang/String;
    //   1645: invokevirtual 49	java/io/PrintStream:println	(Ljava/lang/String;)V
    //   1648: getstatic 37	java/lang/System:out	Ljava/io/PrintStream;
    //   1651: ldc 220
    //   1653: invokevirtual 49	java/io/PrintStream:println	(Ljava/lang/String;)V
    //   1656: ldc_w 370
    //   1659: invokestatic 373	weibo4android/org/json/HTTP:toJSONObject	(Ljava/lang/String;)Lweibo4android/org/json/JSONObject;
    //   1662: astore_0
    //   1663: getstatic 37	java/lang/System:out	Ljava/io/PrintStream;
    //   1666: aload_0
    //   1667: iconst_2
    //   1668: invokevirtual 56	weibo4android/org/json/JSONObject:toString	(I)Ljava/lang/String;
    //   1671: invokevirtual 49	java/io/PrintStream:println	(Ljava/lang/String;)V
    //   1674: getstatic 37	java/lang/System:out	Ljava/io/PrintStream;
    //   1677: aload_0
    //   1678: invokestatic 374	weibo4android/org/json/HTTP:toString	(Lweibo4android/org/json/JSONObject;)Ljava/lang/String;
    //   1681: invokevirtual 49	java/io/PrintStream:println	(Ljava/lang/String;)V
    //   1684: getstatic 37	java/lang/System:out	Ljava/io/PrintStream;
    //   1687: ldc 220
    //   1689: invokevirtual 49	java/io/PrintStream:println	(Ljava/lang/String;)V
    //   1692: ldc_w 376
    //   1695: invokestatic 373	weibo4android/org/json/HTTP:toJSONObject	(Ljava/lang/String;)Lweibo4android/org/json/JSONObject;
    //   1698: astore_0
    //   1699: getstatic 37	java/lang/System:out	Ljava/io/PrintStream;
    //   1702: aload_0
    //   1703: iconst_2
    //   1704: invokevirtual 56	weibo4android/org/json/JSONObject:toString	(I)Ljava/lang/String;
    //   1707: invokevirtual 49	java/io/PrintStream:println	(Ljava/lang/String;)V
    //   1710: getstatic 37	java/lang/System:out	Ljava/io/PrintStream;
    //   1713: aload_0
    //   1714: invokestatic 374	weibo4android/org/json/HTTP:toString	(Lweibo4android/org/json/JSONObject;)Ljava/lang/String;
    //   1717: invokevirtual 49	java/io/PrintStream:println	(Ljava/lang/String;)V
    //   1720: getstatic 37	java/lang/System:out	Ljava/io/PrintStream;
    //   1723: ldc 220
    //   1725: invokevirtual 49	java/io/PrintStream:println	(Ljava/lang/String;)V
    //   1728: new 39	weibo4android/org/json/JSONObject
    //   1731: dup
    //   1732: ldc_w 378
    //   1735: invokespecial 53	weibo4android/org/json/JSONObject:<init>	(Ljava/lang/String;)V
    //   1738: astore_0
    //   1739: getstatic 37	java/lang/System:out	Ljava/io/PrintStream;
    //   1742: aload_0
    //   1743: iconst_2
    //   1744: invokevirtual 56	weibo4android/org/json/JSONObject:toString	(I)Ljava/lang/String;
    //   1747: invokevirtual 49	java/io/PrintStream:println	(Ljava/lang/String;)V
    //   1750: getstatic 37	java/lang/System:out	Ljava/io/PrintStream;
    //   1753: new 291	java/lang/StringBuilder
    //   1756: dup
    //   1757: invokespecial 292	java/lang/StringBuilder:<init>	()V
    //   1760: ldc_w 380
    //   1763: invokevirtual 298	java/lang/StringBuilder:append	(Ljava/lang/String;)Ljava/lang/StringBuilder;
    //   1766: aload_0
    //   1767: ldc_w 382
    //   1770: invokevirtual 385	weibo4android/org/json/JSONObject:isNull	(Ljava/lang/String;)Z
    //   1773: invokevirtual 315	java/lang/StringBuilder:append	(Z)Ljava/lang/StringBuilder;
    //   1776: invokevirtual 306	java/lang/StringBuilder:toString	()Ljava/lang/String;
    //   1779: invokevirtual 49	java/io/PrintStream:println	(Ljava/lang/String;)V
    //   1782: getstatic 37	java/lang/System:out	Ljava/io/PrintStream;
    //   1785: new 291	java/lang/StringBuilder
    //   1788: dup
    //   1789: invokespecial 292	java/lang/StringBuilder:<init>	()V
    //   1792: ldc_w 387
    //   1795: invokevirtual 298	java/lang/StringBuilder:append	(Ljava/lang/String;)Ljava/lang/StringBuilder;
    //   1798: aload_0
    //   1799: ldc_w 382
    //   1802: invokevirtual 390	weibo4android/org/json/JSONObject:has	(Ljava/lang/String;)Z
    //   1805: invokevirtual 315	java/lang/StringBuilder:append	(Z)Ljava/lang/StringBuilder;
    //   1808: invokevirtual 306	java/lang/StringBuilder:toString	()Ljava/lang/String;
    //   1811: invokevirtual 49	java/io/PrintStream:println	(Ljava/lang/String;)V
    //   1814: getstatic 37	java/lang/System:out	Ljava/io/PrintStream;
    //   1817: aload_0
    //   1818: invokestatic 59	weibo4android/org/json/XML:toString	(Ljava/lang/Object;)Ljava/lang/String;
    //   1821: invokevirtual 49	java/io/PrintStream:println	(Ljava/lang/String;)V
    //   1824: getstatic 37	java/lang/System:out	Ljava/io/PrintStream;
    //   1827: aload_0
    //   1828: invokestatic 374	weibo4android/org/json/HTTP:toString	(Lweibo4android/org/json/JSONObject;)Ljava/lang/String;
    //   1831: invokevirtual 49	java/io/PrintStream:println	(Ljava/lang/String;)V
    //   1834: getstatic 37	java/lang/System:out	Ljava/io/PrintStream;
    //   1837: ldc 220
    //   1839: invokevirtual 49	java/io/PrintStream:println	(Ljava/lang/String;)V
    //   1842: ldc_w 392
    //   1845: invokestatic 31	weibo4android/org/json/XML:toJSONObject	(Ljava/lang/String;)Lweibo4android/org/json/JSONObject;
    //   1848: astore_0
    //   1849: getstatic 37	java/lang/System:out	Ljava/io/PrintStream;
    //   1852: aload_0
    //   1853: iconst_2
    //   1854: invokevirtual 56	weibo4android/org/json/JSONObject:toString	(I)Ljava/lang/String;
    //   1857: invokevirtual 49	java/io/PrintStream:println	(Ljava/lang/String;)V
    //   1860: getstatic 37	java/lang/System:out	Ljava/io/PrintStream;
    //   1863: aload_0
    //   1864: invokestatic 59	weibo4android/org/json/XML:toString	(Ljava/lang/Object;)Ljava/lang/String;
    //   1867: invokevirtual 49	java/io/PrintStream:println	(Ljava/lang/String;)V
    //   1870: getstatic 37	java/lang/System:out	Ljava/io/PrintStream;
    //   1873: ldc 220
    //   1875: invokevirtual 49	java/io/PrintStream:println	(Ljava/lang/String;)V
    //   1878: new 39	weibo4android/org/json/JSONObject
    //   1881: dup
    //   1882: ldc_w 394
    //   1885: invokespecial 53	weibo4android/org/json/JSONObject:<init>	(Ljava/lang/String;)V
    //   1888: astore_0
    //   1889: getstatic 37	java/lang/System:out	Ljava/io/PrintStream;
    //   1892: aload_0
    //   1893: iconst_2
    //   1894: invokevirtual 56	weibo4android/org/json/JSONObject:toString	(I)Ljava/lang/String;
    //   1897: invokevirtual 49	java/io/PrintStream:println	(Ljava/lang/String;)V
    //   1900: getstatic 37	java/lang/System:out	Ljava/io/PrintStream;
    //   1903: aload_0
    //   1904: invokestatic 59	weibo4android/org/json/XML:toString	(Ljava/lang/Object;)Ljava/lang/String;
    //   1907: invokevirtual 49	java/io/PrintStream:println	(Ljava/lang/String;)V
    //   1910: getstatic 37	java/lang/System:out	Ljava/io/PrintStream;
    //   1913: ldc 220
    //   1915: invokevirtual 49	java/io/PrintStream:println	(Ljava/lang/String;)V
    //   1918: ldc_w 396
    //   1921: invokestatic 399	weibo4android/org/json/CookieList:toJSONObject	(Ljava/lang/String;)Lweibo4android/org/json/JSONObject;
    //   1924: astore_0
    //   1925: getstatic 37	java/lang/System:out	Ljava/io/PrintStream;
    //   1928: aload_0
    //   1929: iconst_2
    //   1930: invokevirtual 56	weibo4android/org/json/JSONObject:toString	(I)Ljava/lang/String;
    //   1933: invokevirtual 49	java/io/PrintStream:println	(Ljava/lang/String;)V
    //   1936: getstatic 37	java/lang/System:out	Ljava/io/PrintStream;
    //   1939: aload_0
    //   1940: invokestatic 400	weibo4android/org/json/CookieList:toString	(Lweibo4android/org/json/JSONObject;)Ljava/lang/String;
    //   1943: invokevirtual 49	java/io/PrintStream:println	(Ljava/lang/String;)V
    //   1946: getstatic 37	java/lang/System:out	Ljava/io/PrintStream;
    //   1949: ldc 220
    //   1951: invokevirtual 49	java/io/PrintStream:println	(Ljava/lang/String;)V
    //   1954: ldc_w 402
    //   1957: invokestatic 405	weibo4android/org/json/Cookie:toJSONObject	(Ljava/lang/String;)Lweibo4android/org/json/JSONObject;
    //   1960: astore_0
    //   1961: getstatic 37	java/lang/System:out	Ljava/io/PrintStream;
    //   1964: aload_0
    //   1965: iconst_2
    //   1966: invokevirtual 56	weibo4android/org/json/JSONObject:toString	(I)Ljava/lang/String;
    //   1969: invokevirtual 49	java/io/PrintStream:println	(Ljava/lang/String;)V
    //   1972: getstatic 37	java/lang/System:out	Ljava/io/PrintStream;
    //   1975: aload_0
    //   1976: invokestatic 406	weibo4android/org/json/Cookie:toString	(Lweibo4android/org/json/JSONObject;)Ljava/lang/String;
    //   1979: invokevirtual 49	java/io/PrintStream:println	(Ljava/lang/String;)V
    //   1982: getstatic 37	java/lang/System:out	Ljava/io/PrintStream;
    //   1985: ldc 220
    //   1987: invokevirtual 49	java/io/PrintStream:println	(Ljava/lang/String;)V
    //   1990: new 39	weibo4android/org/json/JSONObject
    //   1993: dup
    //   1994: ldc_w 408
    //   1997: invokespecial 53	weibo4android/org/json/JSONObject:<init>	(Ljava/lang/String;)V
    //   2000: astore_0
    //   2001: getstatic 37	java/lang/System:out	Ljava/io/PrintStream;
    //   2004: aload_0
    //   2005: invokevirtual 43	weibo4android/org/json/JSONObject:toString	()Ljava/lang/String;
    //   2008: invokevirtual 49	java/io/PrintStream:println	(Ljava/lang/String;)V
    //   2011: getstatic 37	java/lang/System:out	Ljava/io/PrintStream;
    //   2014: ldc 220
    //   2016: invokevirtual 49	java/io/PrintStream:println	(Ljava/lang/String;)V
    //   2019: new 410	weibo4android/org/json/JSONTokener
    //   2022: dup
    //   2023: ldc_w 412
    //   2026: invokespecial 413	weibo4android/org/json/JSONTokener:<init>	(Ljava/lang/String;)V
    //   2029: astore_0
    //   2030: new 39	weibo4android/org/json/JSONObject
    //   2033: dup
    //   2034: aload_0
    //   2035: invokespecial 416	weibo4android/org/json/JSONObject:<init>	(Lweibo4android/org/json/JSONTokener;)V
    //   2038: astore_1
    //   2039: getstatic 37	java/lang/System:out	Ljava/io/PrintStream;
    //   2042: aload_1
    //   2043: invokevirtual 43	weibo4android/org/json/JSONObject:toString	()Ljava/lang/String;
    //   2046: invokevirtual 49	java/io/PrintStream:println	(Ljava/lang/String;)V
    //   2049: getstatic 37	java/lang/System:out	Ljava/io/PrintStream;
    //   2052: new 291	java/lang/StringBuilder
    //   2055: dup
    //   2056: invokespecial 292	java/lang/StringBuilder:<init>	()V
    //   2059: ldc_w 418
    //   2062: invokevirtual 298	java/lang/StringBuilder:append	(Ljava/lang/String;)Ljava/lang/StringBuilder;
    //   2065: aload_1
    //   2066: ldc_w 420
    //   2069: invokevirtual 423	weibo4android/org/json/JSONObject:optInt	(Ljava/lang/String;)I
    //   2072: invokevirtual 345	java/lang/StringBuilder:append	(I)Ljava/lang/StringBuilder;
    //   2075: invokevirtual 306	java/lang/StringBuilder:toString	()Ljava/lang/String;
    //   2078: invokevirtual 49	java/io/PrintStream:println	(Ljava/lang/String;)V
    //   2081: aload_0
    //   2082: bipush 123
    //   2084: invokevirtual 427	weibo4android/org/json/JSONTokener:skipTo	(C)C
    //   2087: istore 4
    //   2089: getstatic 37	java/lang/System:out	Ljava/io/PrintStream;
    //   2092: iload 4
    //   2094: invokevirtual 430	java/io/PrintStream:println	(I)V
    //   2097: new 39	weibo4android/org/json/JSONObject
    //   2100: dup
    //   2101: aload_0
    //   2102: invokespecial 416	weibo4android/org/json/JSONObject:<init>	(Lweibo4android/org/json/JSONTokener;)V
    //   2105: astore_0
    //   2106: getstatic 37	java/lang/System:out	Ljava/io/PrintStream;
    //   2109: aload_0
    //   2110: invokevirtual 43	weibo4android/org/json/JSONObject:toString	()Ljava/lang/String;
    //   2113: invokevirtual 49	java/io/PrintStream:println	(Ljava/lang/String;)V
    //   2116: getstatic 37	java/lang/System:out	Ljava/io/PrintStream;
    //   2119: ldc 220
    //   2121: invokevirtual 49	java/io/PrintStream:println	(Ljava/lang/String;)V
    //   2124: ldc_w 432
    //   2127: invokestatic 435	weibo4android/org/json/CDL:toJSONArray	(Ljava/lang/String;)Lweibo4android/org/json/JSONArray;
    //   2130: astore_0
    //   2131: getstatic 37	java/lang/System:out	Ljava/io/PrintStream;
    //   2134: aload_0
    //   2135: invokestatic 436	weibo4android/org/json/CDL:toString	(Lweibo4android/org/json/JSONArray;)Ljava/lang/String;
    //   2138: invokevirtual 49	java/io/PrintStream:println	(Ljava/lang/String;)V
    //   2141: getstatic 37	java/lang/System:out	Ljava/io/PrintStream;
    //   2144: ldc 220
    //   2146: invokevirtual 49	java/io/PrintStream:println	(Ljava/lang/String;)V
    //   2149: getstatic 37	java/lang/System:out	Ljava/io/PrintStream;
    //   2152: aload_0
    //   2153: iconst_4
    //   2154: invokevirtual 76	weibo4android/org/json/JSONArray:toString	(I)Ljava/lang/String;
    //   2157: invokevirtual 49	java/io/PrintStream:println	(Ljava/lang/String;)V
    //   2160: getstatic 37	java/lang/System:out	Ljava/io/PrintStream;
    //   2163: ldc 220
    //   2165: invokevirtual 49	java/io/PrintStream:println	(Ljava/lang/String;)V
    //   2168: new 75	weibo4android/org/json/JSONArray
    //   2171: dup
    //   2172: ldc_w 438
    //   2175: invokespecial 197	weibo4android/org/json/JSONArray:<init>	(Ljava/lang/String;)V
    //   2178: astore_0
    //   2179: getstatic 37	java/lang/System:out	Ljava/io/PrintStream;
    //   2182: aload_0
    //   2183: invokevirtual 199	weibo4android/org/json/JSONArray:toString	()Ljava/lang/String;
    //   2186: invokevirtual 49	java/io/PrintStream:println	(Ljava/lang/String;)V
    //   2189: getstatic 37	java/lang/System:out	Ljava/io/PrintStream;
    //   2192: ldc 220
    //   2194: invokevirtual 49	java/io/PrintStream:println	(Ljava/lang/String;)V
    //   2197: getstatic 37	java/lang/System:out	Ljava/io/PrintStream;
    //   2200: aload_0
    //   2201: invokestatic 59	weibo4android/org/json/XML:toString	(Ljava/lang/Object;)Ljava/lang/String;
    //   2204: invokevirtual 49	java/io/PrintStream:println	(Ljava/lang/String;)V
    //   2207: getstatic 37	java/lang/System:out	Ljava/io/PrintStream;
    //   2210: ldc 220
    //   2212: invokevirtual 49	java/io/PrintStream:println	(Ljava/lang/String;)V
    //   2215: new 39	weibo4android/org/json/JSONObject
    //   2218: dup
    //   2219: ldc_w 440
    //   2222: invokespecial 53	weibo4android/org/json/JSONObject:<init>	(Ljava/lang/String;)V
    //   2225: astore_1
    //   2226: getstatic 37	java/lang/System:out	Ljava/io/PrintStream;
    //   2229: aload_1
    //   2230: iconst_4
    //   2231: invokevirtual 56	weibo4android/org/json/JSONObject:toString	(I)Ljava/lang/String;
    //   2234: invokevirtual 49	java/io/PrintStream:println	(Ljava/lang/String;)V
    //   2237: getstatic 37	java/lang/System:out	Ljava/io/PrintStream;
    //   2240: ldc 220
    //   2242: invokevirtual 49	java/io/PrintStream:println	(Ljava/lang/String;)V
    //   2245: aload_1
    //   2246: ldc 166
    //   2248: invokevirtual 312	weibo4android/org/json/JSONObject:getBoolean	(Ljava/lang/String;)Z
    //   2251: ifeq +21 -> 2272
    //   2254: aload_1
    //   2255: ldc 161
    //   2257: invokevirtual 312	weibo4android/org/json/JSONObject:getBoolean	(Ljava/lang/String;)Z
    //   2260: ifne +12 -> 2272
    //   2263: getstatic 37	java/lang/System:out	Ljava/io/PrintStream;
    //   2266: ldc_w 442
    //   2269: invokevirtual 49	java/io/PrintStream:println	(Ljava/lang/String;)V
    //   2272: getstatic 37	java/lang/System:out	Ljava/io/PrintStream;
    //   2275: ldc 220
    //   2277: invokevirtual 49	java/io/PrintStream:println	(Ljava/lang/String;)V
    //   2280: new 39	weibo4android/org/json/JSONObject
    //   2283: dup
    //   2284: aload_1
    //   2285: iconst_4
    //   2286: anewarray 201	java/lang/String
    //   2289: dup
    //   2290: iconst_0
    //   2291: ldc_w 444
    //   2294: aastore
    //   2295: dup
    //   2296: iconst_1
    //   2297: ldc_w 446
    //   2300: aastore
    //   2301: dup
    //   2302: iconst_2
    //   2303: ldc_w 448
    //   2306: aastore
    //   2307: dup
    //   2308: iconst_3
    //   2309: ldc_w 450
    //   2312: aastore
    //   2313: invokespecial 453	weibo4android/org/json/JSONObject:<init>	(Lweibo4android/org/json/JSONObject;[Ljava/lang/String;)V
    //   2316: astore_1
    //   2317: getstatic 37	java/lang/System:out	Ljava/io/PrintStream;
    //   2320: aload_1
    //   2321: iconst_4
    //   2322: invokevirtual 56	weibo4android/org/json/JSONObject:toString	(I)Ljava/lang/String;
    //   2325: invokevirtual 49	java/io/PrintStream:println	(Ljava/lang/String;)V
    //   2328: getstatic 37	java/lang/System:out	Ljava/io/PrintStream;
    //   2331: ldc 220
    //   2333: invokevirtual 49	java/io/PrintStream:println	(Ljava/lang/String;)V
    //   2336: getstatic 37	java/lang/System:out	Ljava/io/PrintStream;
    //   2339: new 90	weibo4android/org/json/JSONStringer
    //   2342: dup
    //   2343: invokespecial 91	weibo4android/org/json/JSONStringer:<init>	()V
    //   2346: invokevirtual 145	weibo4android/org/json/JSONStringer:array	()Lweibo4android/org/json/JSONWriter;
    //   2349: aload_0
    //   2350: invokevirtual 109	weibo4android/org/json/JSONWriter:value	(Ljava/lang/Object;)Lweibo4android/org/json/JSONWriter;
    //   2353: aload_1
    //   2354: invokevirtual 109	weibo4android/org/json/JSONWriter:value	(Ljava/lang/Object;)Lweibo4android/org/json/JSONWriter;
    //   2357: invokevirtual 133	weibo4android/org/json/JSONWriter:endArray	()Lweibo4android/org/json/JSONWriter;
    //   2360: invokevirtual 455	java/io/PrintStream:println	(Ljava/lang/Object;)V
    //   2363: new 39	weibo4android/org/json/JSONObject
    //   2366: dup
    //   2367: ldc_w 457
    //   2370: invokespecial 53	weibo4android/org/json/JSONObject:<init>	(Ljava/lang/String;)V
    //   2373: astore_0
    //   2374: getstatic 37	java/lang/System:out	Ljava/io/PrintStream;
    //   2377: aload_0
    //   2378: iconst_4
    //   2379: invokevirtual 56	weibo4android/org/json/JSONObject:toString	(I)Ljava/lang/String;
    //   2382: invokevirtual 49	java/io/PrintStream:println	(Ljava/lang/String;)V
    //   2385: getstatic 37	java/lang/System:out	Ljava/io/PrintStream;
    //   2388: ldc_w 459
    //   2391: invokevirtual 49	java/io/PrintStream:println	(Ljava/lang/String;)V
    //   2394: getstatic 37	java/lang/System:out	Ljava/io/PrintStream;
    //   2397: new 291	java/lang/StringBuilder
    //   2400: dup
    //   2401: invokespecial 292	java/lang/StringBuilder:<init>	()V
    //   2404: ldc_w 461
    //   2407: invokevirtual 298	java/lang/StringBuilder:append	(Ljava/lang/String;)Ljava/lang/StringBuilder;
    //   2410: aload_0
    //   2411: ldc 234
    //   2413: invokevirtual 342	weibo4android/org/json/JSONObject:getInt	(Ljava/lang/String;)I
    //   2416: invokevirtual 345	java/lang/StringBuilder:append	(I)Ljava/lang/StringBuilder;
    //   2419: invokevirtual 306	java/lang/StringBuilder:toString	()Ljava/lang/String;
    //   2422: invokevirtual 49	java/io/PrintStream:println	(Ljava/lang/String;)V
    //   2425: getstatic 37	java/lang/System:out	Ljava/io/PrintStream;
    //   2428: new 291	java/lang/StringBuilder
    //   2431: dup
    //   2432: invokespecial 292	java/lang/StringBuilder:<init>	()V
    //   2435: ldc_w 463
    //   2438: invokevirtual 298	java/lang/StringBuilder:append	(Ljava/lang/String;)Ljava/lang/StringBuilder;
    //   2441: aload_0
    //   2442: ldc 181
    //   2444: invokevirtual 342	weibo4android/org/json/JSONObject:getInt	(Ljava/lang/String;)I
    //   2447: invokevirtual 345	java/lang/StringBuilder:append	(I)Ljava/lang/StringBuilder;
    //   2450: invokevirtual 306	java/lang/StringBuilder:toString	()Ljava/lang/String;
    //   2453: invokevirtual 49	java/io/PrintStream:println	(Ljava/lang/String;)V
    //   2456: getstatic 37	java/lang/System:out	Ljava/io/PrintStream;
    //   2459: new 291	java/lang/StringBuilder
    //   2462: dup
    //   2463: invokespecial 292	java/lang/StringBuilder:<init>	()V
    //   2466: ldc_w 465
    //   2469: invokevirtual 298	java/lang/StringBuilder:append	(Ljava/lang/String;)Ljava/lang/StringBuilder;
    //   2472: aload_0
    //   2473: ldc_w 467
    //   2476: invokevirtual 342	weibo4android/org/json/JSONObject:getInt	(Ljava/lang/String;)I
    //   2479: invokevirtual 345	java/lang/StringBuilder:append	(I)Ljava/lang/StringBuilder;
    //   2482: invokevirtual 306	java/lang/StringBuilder:toString	()Ljava/lang/String;
    //   2485: invokevirtual 49	java/io/PrintStream:println	(Ljava/lang/String;)V
    //   2488: getstatic 37	java/lang/System:out	Ljava/io/PrintStream;
    //   2491: new 291	java/lang/StringBuilder
    //   2494: dup
    //   2495: invokespecial 292	java/lang/StringBuilder:<init>	()V
    //   2498: ldc_w 469
    //   2501: invokevirtual 298	java/lang/StringBuilder:append	(Ljava/lang/String;)Ljava/lang/StringBuilder;
    //   2504: aload_0
    //   2505: ldc 239
    //   2507: invokevirtual 342	weibo4android/org/json/JSONObject:getInt	(Ljava/lang/String;)I
    //   2510: invokevirtual 345	java/lang/StringBuilder:append	(I)Ljava/lang/StringBuilder;
    //   2513: invokevirtual 306	java/lang/StringBuilder:toString	()Ljava/lang/String;
    //   2516: invokevirtual 49	java/io/PrintStream:println	(Ljava/lang/String;)V
    //   2519: getstatic 37	java/lang/System:out	Ljava/io/PrintStream;
    //   2522: new 291	java/lang/StringBuilder
    //   2525: dup
    //   2526: invokespecial 292	java/lang/StringBuilder:<init>	()V
    //   2529: ldc_w 471
    //   2532: invokevirtual 298	java/lang/StringBuilder:append	(Ljava/lang/String;)Ljava/lang/StringBuilder;
    //   2535: aload_0
    //   2536: ldc_w 473
    //   2539: invokevirtual 342	weibo4android/org/json/JSONObject:getInt	(Ljava/lang/String;)I
    //   2542: invokevirtual 345	java/lang/StringBuilder:append	(I)Ljava/lang/StringBuilder;
    //   2545: invokevirtual 306	java/lang/StringBuilder:toString	()Ljava/lang/String;
    //   2548: invokevirtual 49	java/io/PrintStream:println	(Ljava/lang/String;)V
    //   2551: getstatic 37	java/lang/System:out	Ljava/io/PrintStream;
    //   2554: ldc_w 475
    //   2557: invokevirtual 49	java/io/PrintStream:println	(Ljava/lang/String;)V
    //   2560: getstatic 37	java/lang/System:out	Ljava/io/PrintStream;
    //   2563: new 291	java/lang/StringBuilder
    //   2566: dup
    //   2567: invokespecial 292	java/lang/StringBuilder:<init>	()V
    //   2570: ldc_w 461
    //   2573: invokevirtual 298	java/lang/StringBuilder:append	(Ljava/lang/String;)Ljava/lang/StringBuilder;
    //   2576: aload_0
    //   2577: ldc 234
    //   2579: invokevirtual 479	weibo4android/org/json/JSONObject:getLong	(Ljava/lang/String;)J
    //   2582: invokevirtual 482	java/lang/StringBuilder:append	(J)Ljava/lang/StringBuilder;
    //   2585: invokevirtual 306	java/lang/StringBuilder:toString	()Ljava/lang/String;
    //   2588: invokevirtual 49	java/io/PrintStream:println	(Ljava/lang/String;)V
    //   2591: getstatic 37	java/lang/System:out	Ljava/io/PrintStream;
    //   2594: new 291	java/lang/StringBuilder
    //   2597: dup
    //   2598: invokespecial 292	java/lang/StringBuilder:<init>	()V
    //   2601: ldc_w 463
    //   2604: invokevirtual 298	java/lang/StringBuilder:append	(Ljava/lang/String;)Ljava/lang/StringBuilder;
    //   2607: aload_0
    //   2608: ldc 181
    //   2610: invokevirtual 479	weibo4android/org/json/JSONObject:getLong	(Ljava/lang/String;)J
    //   2613: invokevirtual 482	java/lang/StringBuilder:append	(J)Ljava/lang/StringBuilder;
    //   2616: invokevirtual 306	java/lang/StringBuilder:toString	()Ljava/lang/String;
    //   2619: invokevirtual 49	java/io/PrintStream:println	(Ljava/lang/String;)V
    //   2622: getstatic 37	java/lang/System:out	Ljava/io/PrintStream;
    //   2625: new 291	java/lang/StringBuilder
    //   2628: dup
    //   2629: invokespecial 292	java/lang/StringBuilder:<init>	()V
    //   2632: ldc_w 465
    //   2635: invokevirtual 298	java/lang/StringBuilder:append	(Ljava/lang/String;)Ljava/lang/StringBuilder;
    //   2638: aload_0
    //   2639: ldc_w 467
    //   2642: invokevirtual 479	weibo4android/org/json/JSONObject:getLong	(Ljava/lang/String;)J
    //   2645: invokevirtual 482	java/lang/StringBuilder:append	(J)Ljava/lang/StringBuilder;
    //   2648: invokevirtual 306	java/lang/StringBuilder:toString	()Ljava/lang/String;
    //   2651: invokevirtual 49	java/io/PrintStream:println	(Ljava/lang/String;)V
    //   2654: getstatic 37	java/lang/System:out	Ljava/io/PrintStream;
    //   2657: new 291	java/lang/StringBuilder
    //   2660: dup
    //   2661: invokespecial 292	java/lang/StringBuilder:<init>	()V
    //   2664: ldc_w 469
    //   2667: invokevirtual 298	java/lang/StringBuilder:append	(Ljava/lang/String;)Ljava/lang/StringBuilder;
    //   2670: aload_0
    //   2671: ldc 239
    //   2673: invokevirtual 479	weibo4android/org/json/JSONObject:getLong	(Ljava/lang/String;)J
    //   2676: invokevirtual 482	java/lang/StringBuilder:append	(J)Ljava/lang/StringBuilder;
    //   2679: invokevirtual 306	java/lang/StringBuilder:toString	()Ljava/lang/String;
    //   2682: invokevirtual 49	java/io/PrintStream:println	(Ljava/lang/String;)V
    //   2685: getstatic 37	java/lang/System:out	Ljava/io/PrintStream;
    //   2688: new 291	java/lang/StringBuilder
    //   2691: dup
    //   2692: invokespecial 292	java/lang/StringBuilder:<init>	()V
    //   2695: ldc_w 471
    //   2698: invokevirtual 298	java/lang/StringBuilder:append	(Ljava/lang/String;)Ljava/lang/StringBuilder;
    //   2701: aload_0
    //   2702: ldc_w 473
    //   2705: invokevirtual 479	weibo4android/org/json/JSONObject:getLong	(Ljava/lang/String;)J
    //   2708: invokevirtual 482	java/lang/StringBuilder:append	(J)Ljava/lang/StringBuilder;
    //   2711: invokevirtual 306	java/lang/StringBuilder:toString	()Ljava/lang/String;
    //   2714: invokevirtual 49	java/io/PrintStream:println	(Ljava/lang/String;)V
    //   2717: getstatic 37	java/lang/System:out	Ljava/io/PrintStream;
    //   2720: ldc_w 484
    //   2723: invokevirtual 49	java/io/PrintStream:println	(Ljava/lang/String;)V
    //   2726: getstatic 37	java/lang/System:out	Ljava/io/PrintStream;
    //   2729: new 291	java/lang/StringBuilder
    //   2732: dup
    //   2733: invokespecial 292	java/lang/StringBuilder:<init>	()V
    //   2736: ldc_w 461
    //   2739: invokevirtual 298	java/lang/StringBuilder:append	(Ljava/lang/String;)Ljava/lang/StringBuilder;
    //   2742: aload_0
    //   2743: ldc 234
    //   2745: invokevirtual 302	weibo4android/org/json/JSONObject:getDouble	(Ljava/lang/String;)D
    //   2748: invokevirtual 305	java/lang/StringBuilder:append	(D)Ljava/lang/StringBuilder;
    //   2751: invokevirtual 306	java/lang/StringBuilder:toString	()Ljava/lang/String;
    //   2754: invokevirtual 49	java/io/PrintStream:println	(Ljava/lang/String;)V
    //   2757: getstatic 37	java/lang/System:out	Ljava/io/PrintStream;
    //   2760: new 291	java/lang/StringBuilder
    //   2763: dup
    //   2764: invokespecial 292	java/lang/StringBuilder:<init>	()V
    //   2767: ldc_w 463
    //   2770: invokevirtual 298	java/lang/StringBuilder:append	(Ljava/lang/String;)Ljava/lang/StringBuilder;
    //   2773: aload_0
    //   2774: ldc 181
    //   2776: invokevirtual 302	weibo4android/org/json/JSONObject:getDouble	(Ljava/lang/String;)D
    //   2779: invokevirtual 305	java/lang/StringBuilder:append	(D)Ljava/lang/StringBuilder;
    //   2782: invokevirtual 306	java/lang/StringBuilder:toString	()Ljava/lang/String;
    //   2785: invokevirtual 49	java/io/PrintStream:println	(Ljava/lang/String;)V
    //   2788: getstatic 37	java/lang/System:out	Ljava/io/PrintStream;
    //   2791: new 291	java/lang/StringBuilder
    //   2794: dup
    //   2795: invokespecial 292	java/lang/StringBuilder:<init>	()V
    //   2798: ldc_w 465
    //   2801: invokevirtual 298	java/lang/StringBuilder:append	(Ljava/lang/String;)Ljava/lang/StringBuilder;
    //   2804: aload_0
    //   2805: ldc_w 467
    //   2808: invokevirtual 302	weibo4android/org/json/JSONObject:getDouble	(Ljava/lang/String;)D
    //   2811: invokevirtual 305	java/lang/StringBuilder:append	(D)Ljava/lang/StringBuilder;
    //   2814: invokevirtual 306	java/lang/StringBuilder:toString	()Ljava/lang/String;
    //   2817: invokevirtual 49	java/io/PrintStream:println	(Ljava/lang/String;)V
    //   2820: getstatic 37	java/lang/System:out	Ljava/io/PrintStream;
    //   2823: new 291	java/lang/StringBuilder
    //   2826: dup
    //   2827: invokespecial 292	java/lang/StringBuilder:<init>	()V
    //   2830: ldc_w 469
    //   2833: invokevirtual 298	java/lang/StringBuilder:append	(Ljava/lang/String;)Ljava/lang/StringBuilder;
    //   2836: aload_0
    //   2837: ldc 239
    //   2839: invokevirtual 302	weibo4android/org/json/JSONObject:getDouble	(Ljava/lang/String;)D
    //   2842: invokevirtual 305	java/lang/StringBuilder:append	(D)Ljava/lang/StringBuilder;
    //   2845: invokevirtual 306	java/lang/StringBuilder:toString	()Ljava/lang/String;
    //   2848: invokevirtual 49	java/io/PrintStream:println	(Ljava/lang/String;)V
    //   2851: getstatic 37	java/lang/System:out	Ljava/io/PrintStream;
    //   2854: new 291	java/lang/StringBuilder
    //   2857: dup
    //   2858: invokespecial 292	java/lang/StringBuilder:<init>	()V
    //   2861: ldc_w 471
    //   2864: invokevirtual 298	java/lang/StringBuilder:append	(Ljava/lang/String;)Ljava/lang/StringBuilder;
    //   2867: aload_0
    //   2868: ldc_w 473
    //   2871: invokevirtual 302	weibo4android/org/json/JSONObject:getDouble	(Ljava/lang/String;)D
    //   2874: invokevirtual 305	java/lang/StringBuilder:append	(D)Ljava/lang/StringBuilder;
    //   2877: invokevirtual 306	java/lang/StringBuilder:toString	()Ljava/lang/String;
    //   2880: invokevirtual 49	java/io/PrintStream:println	(Ljava/lang/String;)V
    //   2883: aload_0
    //   2884: ldc_w 486
    //   2887: ldc2_w 182
    //   2890: invokevirtual 489	weibo4android/org/json/JSONObject:put	(Ljava/lang/String;J)Lweibo4android/org/json/JSONObject;
    //   2893: pop
    //   2894: getstatic 37	java/lang/System:out	Ljava/io/PrintStream;
    //   2897: aload_0
    //   2898: iconst_4
    //   2899: invokevirtual 56	weibo4android/org/json/JSONObject:toString	(I)Ljava/lang/String;
    //   2902: invokevirtual 49	java/io/PrintStream:println	(Ljava/lang/String;)V
    //   2905: new 75	weibo4android/org/json/JSONArray
    //   2908: dup
    //   2909: ldc_w 491
    //   2912: invokespecial 197	weibo4android/org/json/JSONArray:<init>	(Ljava/lang/String;)V
    //   2915: astore_1
    //   2916: getstatic 37	java/lang/System:out	Ljava/io/PrintStream;
    //   2919: aload_1
    //   2920: iconst_4
    //   2921: invokevirtual 76	weibo4android/org/json/JSONArray:toString	(I)Ljava/lang/String;
    //   2924: invokevirtual 49	java/io/PrintStream:println	(Ljava/lang/String;)V
    //   2927: getstatic 37	java/lang/System:out	Ljava/io/PrintStream;
    //   2930: ldc_w 493
    //   2933: invokevirtual 49	java/io/PrintStream:println	(Ljava/lang/String;)V
    //   2936: aload_0
    //   2937: invokevirtual 496	weibo4android/org/json/JSONObject:keys	()Ljava/util/Iterator;
    //   2940: astore_1
    //   2941: aload_1
    //   2942: invokeinterface 502 1 0
    //   2947: ifeq +62 -> 3009
    //   2950: aload_1
    //   2951: invokeinterface 506 1 0
    //   2956: checkcast 201	java/lang/String
    //   2959: astore_2
    //   2960: getstatic 37	java/lang/System:out	Ljava/io/PrintStream;
    //   2963: new 291	java/lang/StringBuilder
    //   2966: dup
    //   2967: invokespecial 292	java/lang/StringBuilder:<init>	()V
    //   2970: aload_2
    //   2971: invokevirtual 298	java/lang/StringBuilder:append	(Ljava/lang/String;)Ljava/lang/StringBuilder;
    //   2974: ldc_w 508
    //   2977: invokevirtual 298	java/lang/StringBuilder:append	(Ljava/lang/String;)Ljava/lang/StringBuilder;
    //   2980: aload_0
    //   2981: aload_2
    //   2982: invokevirtual 323	weibo4android/org/json/JSONObject:getString	(Ljava/lang/String;)Ljava/lang/String;
    //   2985: invokevirtual 298	java/lang/StringBuilder:append	(Ljava/lang/String;)Ljava/lang/StringBuilder;
    //   2988: invokevirtual 306	java/lang/StringBuilder:toString	()Ljava/lang/String;
    //   2991: invokevirtual 49	java/io/PrintStream:println	(Ljava/lang/String;)V
    //   2994: goto -53 -> 2941
    //   2997: astore_0
    //   2998: getstatic 37	java/lang/System:out	Ljava/io/PrintStream;
    //   3001: aload_0
    //   3002: invokevirtual 509	java/lang/Exception:toString	()Ljava/lang/String;
    //   3005: invokevirtual 49	java/io/PrintStream:println	(Ljava/lang/String;)V
    //   3008: return
    //   3009: getstatic 37	java/lang/System:out	Ljava/io/PrintStream;
    //   3012: ldc_w 511
    //   3015: invokevirtual 49	java/io/PrintStream:println	(Ljava/lang/String;)V
    //   3018: new 39	weibo4android/org/json/JSONObject
    //   3021: dup
    //   3022: invokespecial 229	weibo4android/org/json/JSONObject:<init>	()V
    //   3025: astore_0
    //   3026: aload_0
    //   3027: ldc_w 513
    //   3030: ldc_w 515
    //   3033: invokevirtual 518	weibo4android/org/json/JSONObject:accumulate	(Ljava/lang/String;Ljava/lang/Object;)Lweibo4android/org/json/JSONObject;
    //   3036: pop
    //   3037: aload_0
    //   3038: ldc_w 513
    //   3041: ldc_w 520
    //   3044: invokevirtual 518	weibo4android/org/json/JSONObject:accumulate	(Ljava/lang/String;Ljava/lang/Object;)Lweibo4android/org/json/JSONObject;
    //   3047: pop
    //   3048: aload_0
    //   3049: ldc_w 513
    //   3052: ldc_w 522
    //   3055: invokevirtual 518	weibo4android/org/json/JSONObject:accumulate	(Ljava/lang/String;Ljava/lang/Object;)Lweibo4android/org/json/JSONObject;
    //   3058: pop
    //   3059: aload_0
    //   3060: ldc_w 513
    //   3063: invokevirtual 266	weibo4android/org/json/JSONObject:getJSONArray	(Ljava/lang/String;)Lweibo4android/org/json/JSONArray;
    //   3066: iconst_5
    //   3067: ldc_w 524
    //   3070: invokevirtual 527	weibo4android/org/json/JSONArray:put	(ILjava/lang/Object;)Lweibo4android/org/json/JSONArray;
    //   3073: pop
    //   3074: getstatic 37	java/lang/System:out	Ljava/io/PrintStream;
    //   3077: aload_0
    //   3078: iconst_4
    //   3079: invokevirtual 56	weibo4android/org/json/JSONObject:toString	(I)Ljava/lang/String;
    //   3082: invokevirtual 49	java/io/PrintStream:println	(Ljava/lang/String;)V
    //   3085: getstatic 37	java/lang/System:out	Ljava/io/PrintStream;
    //   3088: ldc_w 529
    //   3091: invokevirtual 49	java/io/PrintStream:println	(Ljava/lang/String;)V
    //   3094: getstatic 37	java/lang/System:out	Ljava/io/PrintStream;
    //   3097: aload_0
    //   3098: new 531	java/io/StringWriter
    //   3101: dup
    //   3102: invokespecial 532	java/io/StringWriter:<init>	()V
    //   3105: invokevirtual 536	weibo4android/org/json/JSONObject:write	(Ljava/io/Writer;)Ljava/io/Writer;
    //   3108: invokevirtual 455	java/io/PrintStream:println	(Ljava/lang/Object;)V
    //   3111: ldc_w 538
    //   3114: invokestatic 31	weibo4android/org/json/XML:toJSONObject	(Ljava/lang/String;)Lweibo4android/org/json/JSONObject;
    //   3117: astore_0
    //   3118: getstatic 37	java/lang/System:out	Ljava/io/PrintStream;
    //   3121: aload_0
    //   3122: iconst_4
    //   3123: invokevirtual 56	weibo4android/org/json/JSONObject:toString	(I)Ljava/lang/String;
    //   3126: invokevirtual 49	java/io/PrintStream:println	(Ljava/lang/String;)V
    //   3129: getstatic 37	java/lang/System:out	Ljava/io/PrintStream;
    //   3132: aload_0
    //   3133: invokestatic 59	weibo4android/org/json/XML:toString	(Ljava/lang/Object;)Ljava/lang/String;
    //   3136: invokevirtual 49	java/io/PrintStream:println	(Ljava/lang/String;)V
    //   3139: ldc_w 540
    //   3142: invokestatic 31	weibo4android/org/json/XML:toJSONObject	(Ljava/lang/String;)Lweibo4android/org/json/JSONObject;
    //   3145: astore_0
    //   3146: getstatic 37	java/lang/System:out	Ljava/io/PrintStream;
    //   3149: aload_0
    //   3150: iconst_4
    //   3151: invokevirtual 56	weibo4android/org/json/JSONObject:toString	(I)Ljava/lang/String;
    //   3154: invokevirtual 49	java/io/PrintStream:println	(Ljava/lang/String;)V
    //   3157: getstatic 37	java/lang/System:out	Ljava/io/PrintStream;
    //   3160: aload_0
    //   3161: invokestatic 59	weibo4android/org/json/XML:toString	(Ljava/lang/Object;)Ljava/lang/String;
    //   3164: invokevirtual 49	java/io/PrintStream:println	(Ljava/lang/String;)V
    //   3167: ldc_w 540
    //   3170: invokestatic 73	weibo4android/org/json/JSONML:toJSONArray	(Ljava/lang/String;)Lweibo4android/org/json/JSONArray;
    //   3173: astore_0
    //   3174: getstatic 37	java/lang/System:out	Ljava/io/PrintStream;
    //   3177: aload_0
    //   3178: iconst_4
    //   3179: invokevirtual 76	weibo4android/org/json/JSONArray:toString	(I)Ljava/lang/String;
    //   3182: invokevirtual 49	java/io/PrintStream:println	(Ljava/lang/String;)V
    //   3185: getstatic 37	java/lang/System:out	Ljava/io/PrintStream;
    //   3188: aload_0
    //   3189: invokestatic 79	weibo4android/org/json/JSONML:toString	(Lweibo4android/org/json/JSONArray;)Ljava/lang/String;
    //   3192: invokevirtual 49	java/io/PrintStream:println	(Ljava/lang/String;)V
    //   3195: new 39	weibo4android/org/json/JSONObject
    //   3198: dup
    //   3199: aconst_null
    //   3200: invokespecial 543	weibo4android/org/json/JSONObject:<init>	(Ljava/util/Map;)V
    //   3203: astore_0
    //   3204: new 75	weibo4android/org/json/JSONArray
    //   3207: dup
    //   3208: aconst_null
    //   3209: invokespecial 546	weibo4android/org/json/JSONArray:<init>	(Ljava/util/Collection;)V
    //   3212: astore_1
    //   3213: aload_0
    //   3214: ldc_w 513
    //   3217: ldc_w 548
    //   3220: invokevirtual 550	weibo4android/org/json/JSONObject:append	(Ljava/lang/String;Ljava/lang/Object;)Lweibo4android/org/json/JSONObject;
    //   3223: pop
    //   3224: aload_0
    //   3225: ldc_w 513
    //   3228: ldc_w 524
    //   3231: invokevirtual 550	weibo4android/org/json/JSONObject:append	(Ljava/lang/String;Ljava/lang/Object;)Lweibo4android/org/json/JSONObject;
    //   3234: pop
    //   3235: aload_0
    //   3236: ldc_w 552
    //   3239: ldc_w 515
    //   3242: invokevirtual 518	weibo4android/org/json/JSONObject:accumulate	(Ljava/lang/String;Ljava/lang/Object;)Lweibo4android/org/json/JSONObject;
    //   3245: pop
    //   3246: aload_0
    //   3247: ldc_w 552
    //   3250: ldc_w 520
    //   3253: invokevirtual 518	weibo4android/org/json/JSONObject:accumulate	(Ljava/lang/String;Ljava/lang/Object;)Lweibo4android/org/json/JSONObject;
    //   3256: pop
    //   3257: aload_0
    //   3258: ldc_w 552
    //   3261: ldc_w 522
    //   3264: invokevirtual 518	weibo4android/org/json/JSONObject:accumulate	(Ljava/lang/String;Ljava/lang/Object;)Lweibo4android/org/json/JSONObject;
    //   3267: pop
    //   3268: aload_0
    //   3269: ldc_w 554
    //   3272: aload_0
    //   3273: ldc_w 552
    //   3276: invokevirtual 558	weibo4android/org/json/JSONObject:get	(Ljava/lang/String;)Ljava/lang/Object;
    //   3279: invokevirtual 518	weibo4android/org/json/JSONObject:accumulate	(Ljava/lang/String;Ljava/lang/Object;)Lweibo4android/org/json/JSONObject;
    //   3282: pop
    //   3283: aload_0
    //   3284: ldc_w 560
    //   3287: aconst_null
    //   3288: invokevirtual 563	weibo4android/org/json/JSONObject:put	(Ljava/lang/String;Ljava/util/Map;)Lweibo4android/org/json/JSONObject;
    //   3291: pop
    //   3292: aload_0
    //   3293: ldc_w 565
    //   3296: aconst_null
    //   3297: invokevirtual 568	weibo4android/org/json/JSONObject:put	(Ljava/lang/String;Ljava/util/Collection;)Lweibo4android/org/json/JSONObject;
    //   3300: pop
    //   3301: aload_0
    //   3302: ldc_w 569
    //   3305: aload_1
    //   3306: invokevirtual 216	weibo4android/org/json/JSONObject:put	(Ljava/lang/String;Ljava/lang/Object;)Lweibo4android/org/json/JSONObject;
    //   3309: pop
    //   3310: aload_1
    //   3311: aconst_null
    //   3312: invokevirtual 572	weibo4android/org/json/JSONArray:put	(Ljava/util/Map;)Lweibo4android/org/json/JSONArray;
    //   3315: pop
    //   3316: aload_1
    //   3317: aconst_null
    //   3318: invokevirtual 575	weibo4android/org/json/JSONArray:put	(Ljava/util/Collection;)Lweibo4android/org/json/JSONArray;
    //   3321: pop
    //   3322: getstatic 37	java/lang/System:out	Ljava/io/PrintStream;
    //   3325: aload_0
    //   3326: iconst_4
    //   3327: invokevirtual 56	weibo4android/org/json/JSONObject:toString	(I)Ljava/lang/String;
    //   3330: invokevirtual 49	java/io/PrintStream:println	(Ljava/lang/String;)V
    //   3333: new 39	weibo4android/org/json/JSONObject
    //   3336: dup
    //   3337: ldc_w 577
    //   3340: invokespecial 53	weibo4android/org/json/JSONObject:<init>	(Ljava/lang/String;)V
    //   3343: astore_0
    //   3344: getstatic 37	java/lang/System:out	Ljava/io/PrintStream;
    //   3347: aload_0
    //   3348: iconst_4
    //   3349: invokevirtual 56	weibo4android/org/json/JSONObject:toString	(I)Ljava/lang/String;
    //   3352: invokevirtual 49	java/io/PrintStream:println	(Ljava/lang/String;)V
    //   3355: new 75	weibo4android/org/json/JSONArray
    //   3358: dup
    //   3359: ldc_w 579
    //   3362: invokespecial 197	weibo4android/org/json/JSONArray:<init>	(Ljava/lang/String;)V
    //   3365: astore_1
    //   3366: getstatic 37	java/lang/System:out	Ljava/io/PrintStream;
    //   3369: aload_1
    //   3370: invokevirtual 199	weibo4android/org/json/JSONArray:toString	()Ljava/lang/String;
    //   3373: invokevirtual 49	java/io/PrintStream:println	(Ljava/lang/String;)V
    //   3376: ldc_w 581
    //   3379: invokestatic 31	weibo4android/org/json/XML:toJSONObject	(Ljava/lang/String;)Lweibo4android/org/json/JSONObject;
    //   3382: astore_2
    //   3383: getstatic 37	java/lang/System:out	Ljava/io/PrintStream;
    //   3386: aload_2
    //   3387: iconst_2
    //   3388: invokevirtual 56	weibo4android/org/json/JSONObject:toString	(I)Ljava/lang/String;
    //   3391: invokevirtual 49	java/io/PrintStream:println	(Ljava/lang/String;)V
    //   3394: getstatic 37	java/lang/System:out	Ljava/io/PrintStream;
    //   3397: aload_2
    //   3398: invokestatic 59	weibo4android/org/json/XML:toString	(Ljava/lang/Object;)Ljava/lang/String;
    //   3401: invokevirtual 49	java/io/PrintStream:println	(Ljava/lang/String;)V
    //   3404: getstatic 37	java/lang/System:out	Ljava/io/PrintStream;
    //   3407: ldc 220
    //   3409: invokevirtual 49	java/io/PrintStream:println	(Ljava/lang/String;)V
    //   3412: ldc_w 581
    //   3415: invokestatic 73	weibo4android/org/json/JSONML:toJSONArray	(Ljava/lang/String;)Lweibo4android/org/json/JSONArray;
    //   3418: astore_0
    //   3419: getstatic 37	java/lang/System:out	Ljava/io/PrintStream;
    //   3422: aload_0
    //   3423: iconst_4
    //   3424: invokevirtual 76	weibo4android/org/json/JSONArray:toString	(I)Ljava/lang/String;
    //   3427: invokevirtual 49	java/io/PrintStream:println	(Ljava/lang/String;)V
    //   3430: getstatic 37	java/lang/System:out	Ljava/io/PrintStream;
    //   3433: aload_0
    //   3434: invokestatic 79	weibo4android/org/json/JSONML:toString	(Lweibo4android/org/json/JSONArray;)Ljava/lang/String;
    //   3437: invokevirtual 49	java/io/PrintStream:println	(Ljava/lang/String;)V
    //   3440: getstatic 37	java/lang/System:out	Ljava/io/PrintStream;
    //   3443: ldc 220
    //   3445: invokevirtual 49	java/io/PrintStream:println	(Ljava/lang/String;)V
    //   3448: getstatic 37	java/lang/System:out	Ljava/io/PrintStream;
    //   3451: ldc_w 583
    //   3454: invokevirtual 49	java/io/PrintStream:println	(Ljava/lang/String;)V
    //   3457: getstatic 37	java/lang/System:out	Ljava/io/PrintStream;
    //   3460: ldc_w 585
    //   3463: invokevirtual 588	java/io/PrintStream:print	(Ljava/lang/String;)V
    //   3466: new 75	weibo4android/org/json/JSONArray
    //   3469: dup
    //   3470: invokespecial 232	weibo4android/org/json/JSONArray:<init>	()V
    //   3473: astore_0
    //   3474: aload_0
    //   3475: ldc2_w 589
    //   3478: invokevirtual 274	weibo4android/org/json/JSONArray:put	(D)Lweibo4android/org/json/JSONArray;
    //   3481: pop
    //   3482: aload_0
    //   3483: ldc2_w 591
    //   3486: invokevirtual 274	weibo4android/org/json/JSONArray:put	(D)Lweibo4android/org/json/JSONArray;
    //   3489: pop
    //   3490: getstatic 37	java/lang/System:out	Ljava/io/PrintStream;
    //   3493: aload_0
    //   3494: invokevirtual 199	weibo4android/org/json/JSONArray:toString	()Ljava/lang/String;
    //   3497: invokevirtual 49	java/io/PrintStream:println	(Ljava/lang/String;)V
    //   3500: getstatic 37	java/lang/System:out	Ljava/io/PrintStream;
    //   3503: ldc_w 585
    //   3506: invokevirtual 588	java/io/PrintStream:print	(Ljava/lang/String;)V
    //   3509: getstatic 37	java/lang/System:out	Ljava/io/PrintStream;
    //   3512: aload_2
    //   3513: ldc_w 513
    //   3516: invokevirtual 302	weibo4android/org/json/JSONObject:getDouble	(Ljava/lang/String;)D
    //   3519: invokevirtual 595	java/io/PrintStream:println	(D)V
    //   3522: getstatic 37	java/lang/System:out	Ljava/io/PrintStream;
    //   3525: ldc_w 585
    //   3528: invokevirtual 588	java/io/PrintStream:print	(Ljava/lang/String;)V
    //   3531: getstatic 37	java/lang/System:out	Ljava/io/PrintStream;
    //   3534: aload_2
    //   3535: ldc_w 597
    //   3538: invokevirtual 302	weibo4android/org/json/JSONObject:getDouble	(Ljava/lang/String;)D
    //   3541: invokevirtual 595	java/io/PrintStream:println	(D)V
    //   3544: getstatic 37	java/lang/System:out	Ljava/io/PrintStream;
    //   3547: ldc_w 585
    //   3550: invokevirtual 588	java/io/PrintStream:print	(Ljava/lang/String;)V
    //   3553: getstatic 37	java/lang/System:out	Ljava/io/PrintStream;
    //   3556: aload_2
    //   3557: aconst_null
    //   3558: ldc_w 597
    //   3561: invokevirtual 216	weibo4android/org/json/JSONObject:put	(Ljava/lang/String;Ljava/lang/Object;)Lweibo4android/org/json/JSONObject;
    //   3564: invokevirtual 455	java/io/PrintStream:println	(Ljava/lang/Object;)V
    //   3567: getstatic 37	java/lang/System:out	Ljava/io/PrintStream;
    //   3570: ldc_w 585
    //   3573: invokevirtual 588	java/io/PrintStream:print	(Ljava/lang/String;)V
    //   3576: getstatic 37	java/lang/System:out	Ljava/io/PrintStream;
    //   3579: aload_0
    //   3580: iconst_0
    //   3581: invokevirtual 600	weibo4android/org/json/JSONArray:getDouble	(I)D
    //   3584: invokevirtual 595	java/io/PrintStream:println	(D)V
    //   3587: getstatic 37	java/lang/System:out	Ljava/io/PrintStream;
    //   3590: ldc_w 585
    //   3593: invokevirtual 588	java/io/PrintStream:print	(Ljava/lang/String;)V
    //   3596: getstatic 37	java/lang/System:out	Ljava/io/PrintStream;
    //   3599: aload_0
    //   3600: iconst_m1
    //   3601: invokevirtual 603	weibo4android/org/json/JSONArray:get	(I)Ljava/lang/Object;
    //   3604: invokevirtual 455	java/io/PrintStream:println	(Ljava/lang/Object;)V
    //   3607: getstatic 37	java/lang/System:out	Ljava/io/PrintStream;
    //   3610: ldc_w 585
    //   3613: invokevirtual 588	java/io/PrintStream:print	(Ljava/lang/String;)V
    //   3616: getstatic 37	java/lang/System:out	Ljava/io/PrintStream;
    //   3619: aload_0
    //   3620: ldc2_w 591
    //   3623: invokevirtual 274	weibo4android/org/json/JSONArray:put	(D)Lweibo4android/org/json/JSONArray;
    //   3626: invokevirtual 455	java/io/PrintStream:println	(Ljava/lang/Object;)V
    //   3629: getstatic 37	java/lang/System:out	Ljava/io/PrintStream;
    //   3632: ldc_w 585
    //   3635: invokevirtual 588	java/io/PrintStream:print	(Ljava/lang/String;)V
    //   3638: ldc_w 605
    //   3641: invokestatic 31	weibo4android/org/json/XML:toJSONObject	(Ljava/lang/String;)Lweibo4android/org/json/JSONObject;
    //   3644: astore_0
    //   3645: getstatic 37	java/lang/System:out	Ljava/io/PrintStream;
    //   3648: ldc_w 585
    //   3651: invokevirtual 588	java/io/PrintStream:print	(Ljava/lang/String;)V
    //   3654: ldc_w 607
    //   3657: invokestatic 31	weibo4android/org/json/XML:toJSONObject	(Ljava/lang/String;)Lweibo4android/org/json/JSONObject;
    //   3660: astore_1
    //   3661: aload_1
    //   3662: astore_0
    //   3663: getstatic 37	java/lang/System:out	Ljava/io/PrintStream;
    //   3666: ldc_w 585
    //   3669: invokevirtual 588	java/io/PrintStream:print	(Ljava/lang/String;)V
    //   3672: ldc_w 609
    //   3675: invokestatic 31	weibo4android/org/json/XML:toJSONObject	(Ljava/lang/String;)Lweibo4android/org/json/JSONObject;
    //   3678: astore_1
    //   3679: aload_1
    //   3680: astore_0
    //   3681: getstatic 37	java/lang/System:out	Ljava/io/PrintStream;
    //   3684: ldc_w 585
    //   3687: invokevirtual 588	java/io/PrintStream:print	(Ljava/lang/String;)V
    //   3690: new 75	weibo4android/org/json/JSONArray
    //   3693: dup
    //   3694: new 4	java/lang/Object
    //   3697: dup
    //   3698: invokespecial 11	java/lang/Object:<init>	()V
    //   3701: invokespecial 198	weibo4android/org/json/JSONArray:<init>	(Ljava/lang/Object;)V
    //   3704: astore_1
    //   3705: getstatic 37	java/lang/System:out	Ljava/io/PrintStream;
    //   3708: aload_1
    //   3709: invokevirtual 199	weibo4android/org/json/JSONArray:toString	()Ljava/lang/String;
    //   3712: invokevirtual 49	java/io/PrintStream:println	(Ljava/lang/String;)V
    //   3715: getstatic 37	java/lang/System:out	Ljava/io/PrintStream;
    //   3718: ldc_w 585
    //   3721: invokevirtual 588	java/io/PrintStream:print	(Ljava/lang/String;)V
    //   3724: new 75	weibo4android/org/json/JSONArray
    //   3727: dup
    //   3728: ldc_w 611
    //   3731: invokespecial 197	weibo4android/org/json/JSONArray:<init>	(Ljava/lang/String;)V
    //   3734: astore_1
    //   3735: getstatic 37	java/lang/System:out	Ljava/io/PrintStream;
    //   3738: aload_1
    //   3739: invokevirtual 199	weibo4android/org/json/JSONArray:toString	()Ljava/lang/String;
    //   3742: invokevirtual 49	java/io/PrintStream:println	(Ljava/lang/String;)V
    //   3745: getstatic 37	java/lang/System:out	Ljava/io/PrintStream;
    //   3748: ldc_w 585
    //   3751: invokevirtual 588	java/io/PrintStream:print	(Ljava/lang/String;)V
    //   3754: ldc_w 613
    //   3757: invokestatic 73	weibo4android/org/json/JSONML:toJSONArray	(Ljava/lang/String;)Lweibo4android/org/json/JSONArray;
    //   3760: astore_1
    //   3761: getstatic 37	java/lang/System:out	Ljava/io/PrintStream;
    //   3764: aload_1
    //   3765: iconst_4
    //   3766: invokevirtual 76	weibo4android/org/json/JSONArray:toString	(I)Ljava/lang/String;
    //   3769: invokevirtual 49	java/io/PrintStream:println	(Ljava/lang/String;)V
    //   3772: getstatic 37	java/lang/System:out	Ljava/io/PrintStream;
    //   3775: ldc_w 585
    //   3778: invokevirtual 588	java/io/PrintStream:print	(Ljava/lang/String;)V
    //   3781: ldc_w 615
    //   3784: invokestatic 73	weibo4android/org/json/JSONML:toJSONArray	(Ljava/lang/String;)Lweibo4android/org/json/JSONArray;
    //   3787: astore_1
    //   3788: getstatic 37	java/lang/System:out	Ljava/io/PrintStream;
    //   3791: aload_1
    //   3792: iconst_4
    //   3793: invokevirtual 76	weibo4android/org/json/JSONArray:toString	(I)Ljava/lang/String;
    //   3796: invokevirtual 49	java/io/PrintStream:println	(Ljava/lang/String;)V
    //   3799: getstatic 37	java/lang/System:out	Ljava/io/PrintStream;
    //   3802: ldc_w 585
    //   3805: invokevirtual 588	java/io/PrintStream:print	(Ljava/lang/String;)V
    //   3808: new 39	weibo4android/org/json/JSONObject
    //   3811: dup
    //   3812: ldc_w 617
    //   3815: invokespecial 53	weibo4android/org/json/JSONObject:<init>	(Ljava/lang/String;)V
    //   3818: astore_1
    //   3819: getstatic 37	java/lang/System:out	Ljava/io/PrintStream;
    //   3822: aload_1
    //   3823: iconst_4
    //   3824: invokevirtual 56	weibo4android/org/json/JSONObject:toString	(I)Ljava/lang/String;
    //   3827: invokevirtual 49	java/io/PrintStream:println	(Ljava/lang/String;)V
    //   3830: aload_1
    //   3831: astore_0
    //   3832: getstatic 37	java/lang/System:out	Ljava/io/PrintStream;
    //   3835: ldc_w 585
    //   3838: invokevirtual 588	java/io/PrintStream:print	(Ljava/lang/String;)V
    //   3841: new 90	weibo4android/org/json/JSONStringer
    //   3844: dup
    //   3845: invokespecial 91	weibo4android/org/json/JSONStringer:<init>	()V
    //   3848: invokevirtual 95	weibo4android/org/json/JSONStringer:object	()Lweibo4android/org/json/JSONWriter;
    //   3851: ldc_w 619
    //   3854: invokevirtual 103	weibo4android/org/json/JSONWriter:key	(Ljava/lang/String;)Lweibo4android/org/json/JSONWriter;
    //   3857: ldc 105
    //   3859: invokevirtual 109	weibo4android/org/json/JSONWriter:value	(Ljava/lang/Object;)Lweibo4android/org/json/JSONWriter;
    //   3862: ldc_w 619
    //   3865: invokevirtual 103	weibo4android/org/json/JSONWriter:key	(Ljava/lang/String;)Lweibo4android/org/json/JSONWriter;
    //   3868: ldc 113
    //   3870: invokevirtual 109	weibo4android/org/json/JSONWriter:value	(Ljava/lang/Object;)Lweibo4android/org/json/JSONWriter;
    //   3873: invokevirtual 130	weibo4android/org/json/JSONWriter:endObject	()Lweibo4android/org/json/JSONWriter;
    //   3876: invokevirtual 140	java/lang/Object:toString	()Ljava/lang/String;
    //   3879: pop
    //   3880: getstatic 37	java/lang/System:out	Ljava/io/PrintStream;
    //   3883: aload_0
    //   3884: iconst_4
    //   3885: invokevirtual 56	weibo4android/org/json/JSONObject:toString	(I)Ljava/lang/String;
    //   3888: invokevirtual 49	java/io/PrintStream:println	(Ljava/lang/String;)V
    //   3891: return
    //   3892: astore_0
    //   3893: getstatic 37	java/lang/System:out	Ljava/io/PrintStream;
    //   3896: aload_0
    //   3897: invokevirtual 455	java/io/PrintStream:println	(Ljava/lang/Object;)V
    //   3900: return
    //   3901: getstatic 37	java/lang/System:out	Ljava/io/PrintStream;
    //   3904: aload_1
    //   3905: invokevirtual 455	java/io/PrintStream:println	(Ljava/lang/Object;)V
    //   3908: goto -408 -> 3500
    //   3911: astore_1
    //   3912: getstatic 37	java/lang/System:out	Ljava/io/PrintStream;
    //   3915: aload_1
    //   3916: invokevirtual 455	java/io/PrintStream:println	(Ljava/lang/Object;)V
    //   3919: goto -397 -> 3522
    //   3922: astore_1
    //   3923: getstatic 37	java/lang/System:out	Ljava/io/PrintStream;
    //   3926: aload_1
    //   3927: invokevirtual 455	java/io/PrintStream:println	(Ljava/lang/Object;)V
    //   3930: goto -386 -> 3544
    //   3933: astore_1
    //   3934: getstatic 37	java/lang/System:out	Ljava/io/PrintStream;
    //   3937: aload_1
    //   3938: invokevirtual 455	java/io/PrintStream:println	(Ljava/lang/Object;)V
    //   3941: goto -374 -> 3567
    //   3944: astore_1
    //   3945: getstatic 37	java/lang/System:out	Ljava/io/PrintStream;
    //   3948: aload_1
    //   3949: invokevirtual 455	java/io/PrintStream:println	(Ljava/lang/Object;)V
    //   3952: goto -365 -> 3587
    //   3955: astore_1
    //   3956: getstatic 37	java/lang/System:out	Ljava/io/PrintStream;
    //   3959: aload_1
    //   3960: invokevirtual 455	java/io/PrintStream:println	(Ljava/lang/Object;)V
    //   3963: goto -356 -> 3607
    //   3966: astore_0
    //   3967: getstatic 37	java/lang/System:out	Ljava/io/PrintStream;
    //   3970: aload_0
    //   3971: invokevirtual 455	java/io/PrintStream:println	(Ljava/lang/Object;)V
    //   3974: goto -345 -> 3629
    //   3977: astore_0
    //   3978: getstatic 37	java/lang/System:out	Ljava/io/PrintStream;
    //   3981: aload_0
    //   3982: invokevirtual 455	java/io/PrintStream:println	(Ljava/lang/Object;)V
    //   3985: aload_2
    //   3986: astore_0
    //   3987: goto -342 -> 3645
    //   3990: astore_1
    //   3991: getstatic 37	java/lang/System:out	Ljava/io/PrintStream;
    //   3994: aload_1
    //   3995: invokevirtual 455	java/io/PrintStream:println	(Ljava/lang/Object;)V
    //   3998: goto -335 -> 3663
    //   4001: astore_1
    //   4002: getstatic 37	java/lang/System:out	Ljava/io/PrintStream;
    //   4005: aload_1
    //   4006: invokevirtual 455	java/io/PrintStream:println	(Ljava/lang/Object;)V
    //   4009: goto -328 -> 3681
    //   4012: astore_1
    //   4013: getstatic 37	java/lang/System:out	Ljava/io/PrintStream;
    //   4016: aload_1
    //   4017: invokevirtual 455	java/io/PrintStream:println	(Ljava/lang/Object;)V
    //   4020: goto -305 -> 3715
    //   4023: astore_1
    //   4024: getstatic 37	java/lang/System:out	Ljava/io/PrintStream;
    //   4027: aload_1
    //   4028: invokevirtual 455	java/io/PrintStream:println	(Ljava/lang/Object;)V
    //   4031: goto -286 -> 3745
    //   4034: astore_1
    //   4035: getstatic 37	java/lang/System:out	Ljava/io/PrintStream;
    //   4038: aload_1
    //   4039: invokevirtual 455	java/io/PrintStream:println	(Ljava/lang/Object;)V
    //   4042: goto -270 -> 3772
    //   4045: astore_1
    //   4046: getstatic 37	java/lang/System:out	Ljava/io/PrintStream;
    //   4049: aload_1
    //   4050: invokevirtual 455	java/io/PrintStream:println	(Ljava/lang/Object;)V
    //   4053: goto -254 -> 3799
    //   4056: getstatic 37	java/lang/System:out	Ljava/io/PrintStream;
    //   4059: aload_2
    //   4060: invokevirtual 455	java/io/PrintStream:println	(Ljava/lang/Object;)V
    //   4063: goto -231 -> 3832
    //   4066: astore_2
    //   4067: aload_1
    //   4068: astore_0
    //   4069: goto -13 -> 4056
    //   4072: astore_1
    //   4073: goto -172 -> 3901
    //   4076: astore_3
    //   4077: aload_1
    //   4078: astore_0
    //   4079: aload_3
    //   4080: astore_1
    //   4081: goto -180 -> 3901
    //   4084: astore_2
    //   4085: goto -29 -> 4056
    //
    // Exception table:
    //   from	to	target	type
    //   14	2272	2997	java/lang/Exception
    //   2272	2941	2997	java/lang/Exception
    //   2941	2994	2997	java/lang/Exception
    //   3009	3466	2997	java/lang/Exception
    //   3500	3509	2997	java/lang/Exception
    //   3522	3531	2997	java/lang/Exception
    //   3544	3553	2997	java/lang/Exception
    //   3567	3576	2997	java/lang/Exception
    //   3587	3596	2997	java/lang/Exception
    //   3607	3616	2997	java/lang/Exception
    //   3629	3638	2997	java/lang/Exception
    //   3645	3654	2997	java/lang/Exception
    //   3663	3672	2997	java/lang/Exception
    //   3681	3690	2997	java/lang/Exception
    //   3715	3724	2997	java/lang/Exception
    //   3745	3754	2997	java/lang/Exception
    //   3772	3781	2997	java/lang/Exception
    //   3799	3808	2997	java/lang/Exception
    //   3832	3841	2997	java/lang/Exception
    //   3893	3900	2997	java/lang/Exception
    //   3901	3908	2997	java/lang/Exception
    //   3912	3919	2997	java/lang/Exception
    //   3923	3930	2997	java/lang/Exception
    //   3934	3941	2997	java/lang/Exception
    //   3945	3952	2997	java/lang/Exception
    //   3956	3963	2997	java/lang/Exception
    //   3967	3974	2997	java/lang/Exception
    //   3978	3985	2997	java/lang/Exception
    //   3991	3998	2997	java/lang/Exception
    //   4002	4009	2997	java/lang/Exception
    //   4013	4020	2997	java/lang/Exception
    //   4024	4031	2997	java/lang/Exception
    //   4035	4042	2997	java/lang/Exception
    //   4046	4053	2997	java/lang/Exception
    //   4056	4063	2997	java/lang/Exception
    //   3841	3891	3892	java/lang/Exception
    //   3509	3522	3911	java/lang/Exception
    //   3531	3544	3922	java/lang/Exception
    //   3553	3567	3933	java/lang/Exception
    //   3576	3587	3944	java/lang/Exception
    //   3596	3607	3955	java/lang/Exception
    //   3616	3629	3966	java/lang/Exception
    //   3638	3645	3977	java/lang/Exception
    //   3654	3661	3990	java/lang/Exception
    //   3672	3679	4001	java/lang/Exception
    //   3690	3715	4012	java/lang/Exception
    //   3724	3745	4023	java/lang/Exception
    //   3754	3772	4034	java/lang/Exception
    //   3781	3799	4045	java/lang/Exception
    //   3819	3830	4066	java/lang/Exception
    //   3474	3500	4072	java/lang/Exception
    //   3466	3474	4076	java/lang/Exception
    //   3808	3819	4084	java/lang/Exception
  }
}

/* Location:           C:\Users\User\dex2jar-2.0\dex\qting\classes-dex2jar.jar
 * Qualified Name:     weibo4android.org.json.Test
 * JD-Core Version:    0.6.2
 */