package com.taobao.munion.base.caches;

public class n
{
  public static final String a = "mmusdk_cache";
  public static final String b = "content";
  public static final String c = "meta";
  public static final String d = "name";
  public static final String e = "(?<=meta name=\"mmusdk_cache\" content=\").*?(?=\")";

  // ERROR //
  public java.util.List<b.a> a(String paramString)
  {
    // Byte code:
    //   0: ldc 20
    //   2: invokestatic 34	java/util/regex/Pattern:compile	(Ljava/lang/String;)Ljava/util/regex/Pattern;
    //   5: aload_1
    //   6: invokevirtual 38	java/util/regex/Pattern:matcher	(Ljava/lang/CharSequence;)Ljava/util/regex/Matcher;
    //   9: astore_3
    //   10: aconst_null
    //   11: astore_1
    //   12: aload_1
    //   13: astore_2
    //   14: aload_3
    //   15: invokevirtual 44	java/util/regex/Matcher:find	()Z
    //   18: ifeq +53 -> 71
    //   21: aload_1
    //   22: ifnonnull +59 -> 81
    //   25: new 46	java/util/ArrayList
    //   28: dup
    //   29: invokespecial 47	java/util/ArrayList:<init>	()V
    //   32: astore_2
    //   33: aload_2
    //   34: astore_1
    //   35: new 49	com/taobao/munion/base/caches/b$a
    //   38: dup
    //   39: invokespecial 50	com/taobao/munion/base/caches/b$a:<init>	()V
    //   42: astore_2
    //   43: aload_2
    //   44: aload_3
    //   45: invokevirtual 54	java/util/regex/Matcher:group	()Ljava/lang/String;
    //   48: invokevirtual 57	com/taobao/munion/base/caches/b$a:a	(Ljava/lang/String;)V
    //   51: aload_1
    //   52: aload_2
    //   53: invokeinterface 63 2 0
    //   58: pop
    //   59: goto -47 -> 12
    //   62: astore_2
    //   63: aconst_null
    //   64: astore_1
    //   65: aload_2
    //   66: invokevirtual 66	java/lang/Exception:printStackTrace	()V
    //   69: aload_1
    //   70: astore_2
    //   71: aload_2
    //   72: areturn
    //   73: astore_2
    //   74: goto -9 -> 65
    //   77: astore_2
    //   78: goto -13 -> 65
    //   81: goto -46 -> 35
    //
    // Exception table:
    //   from	to	target	type
    //   0	10	62	java/lang/Exception
    //   35	59	73	java/lang/Exception
    //   14	21	77	java/lang/Exception
    //   25	33	77	java/lang/Exception
  }
}

/* Location:           C:\Users\User\dex2jar-2.0\dex\qting\classes-dex2jar.jar
 * Qualified Name:     com.taobao.munion.base.caches.n
 * JD-Core Version:    0.6.2
 */