package com.intowow.sdk.b;

import java.util.concurrent.ExecutorService;
import org.json.JSONObject;

public class d
{
  private ExecutorService a = null;

  public void a(String paramString1, String paramString2, a parama)
  {
    try
    {
      this.a.execute(new b(paramString1, paramString2, parama));
      return;
    }
    finally
    {
      paramString1 = finally;
    }
    throw paramString1;
  }

  public static abstract interface a
  {
    public abstract void a(int paramInt);

    public abstract void a(JSONObject paramJSONObject);
  }

  private class b
    implements Runnable
  {
    public final String a;
    public final d.a b;

    public b(String paramString1, String parama, d.a arg4)
    {
      paramString1 = new StringBuilder(String.valueOf(paramString1));
      this$1 = parama;
      if (parama == null)
        this$1 = "";
      this.a = d.this;
      Object localObject;
      this.b = localObject;
    }

    // ERROR //
    public void run()
    {
      // Byte code:
      //   0: iconst_m1
      //   1: istore 9
      //   3: new 54	java/net/URL
      //   6: dup
      //   7: aload_0
      //   8: getfield 44	com/intowow/sdk/b/d$b:a	Ljava/lang/String;
      //   11: invokespecial 55	java/net/URL:<init>	(Ljava/lang/String;)V
      //   14: astore_1
      //   15: getstatic 60	com/intowow/sdk/a/e:a	Z
      //   18: ifeq +19 -> 37
      //   21: ldc 62
      //   23: iconst_1
      //   24: anewarray 4	java/lang/Object
      //   27: dup
      //   28: iconst_0
      //   29: aload_0
      //   30: getfield 44	com/intowow/sdk/b/d$b:a	Ljava/lang/String;
      //   33: aastore
      //   34: invokestatic 67	com/intowow/sdk/j/h:a	(Ljava/lang/String;[Ljava/lang/Object;)V
      //   37: aload_1
      //   38: invokevirtual 71	java/net/URL:openConnection	()Ljava/net/URLConnection;
      //   41: checkcast 73	java/net/HttpURLConnection
      //   44: astore_1
      //   45: aload_1
      //   46: ldc 74
      //   48: invokevirtual 78	java/net/HttpURLConnection:setConnectTimeout	(I)V
      //   51: aload_1
      //   52: ldc 80
      //   54: invokevirtual 83	java/net/HttpURLConnection:setRequestMethod	(Ljava/lang/String;)V
      //   57: aload_1
      //   58: iconst_0
      //   59: invokevirtual 87	java/net/HttpURLConnection:setInstanceFollowRedirects	(Z)V
      //   62: aload_1
      //   63: ldc 89
      //   65: ldc 91
      //   67: invokevirtual 95	java/net/HttpURLConnection:setRequestProperty	(Ljava/lang/String;Ljava/lang/String;)V
      //   70: aload_1
      //   71: ldc 97
      //   73: ldc 99
      //   75: invokevirtual 102	java/net/HttpURLConnection:addRequestProperty	(Ljava/lang/String;Ljava/lang/String;)V
      //   78: aload_1
      //   79: invokevirtual 105	java/net/HttpURLConnection:connect	()V
      //   82: aload_1
      //   83: invokevirtual 109	java/net/HttpURLConnection:getResponseCode	()I
      //   86: istore 8
      //   88: iload 8
      //   90: sipush 200
      //   93: if_icmpeq +70 -> 163
      //   96: iconst_0
      //   97: ifeq +11 -> 108
      //   100: new 111	java/lang/NullPointerException
      //   103: dup
      //   104: invokespecial 112	java/lang/NullPointerException:<init>	()V
      //   107: athrow
      //   108: iconst_0
      //   109: ifeq +11 -> 120
      //   112: new 111	java/lang/NullPointerException
      //   115: dup
      //   116: invokespecial 112	java/lang/NullPointerException:<init>	()V
      //   119: athrow
      //   120: aload_1
      //   121: ifnull +7 -> 128
      //   124: aload_1
      //   125: invokevirtual 115	java/net/HttpURLConnection:disconnect	()V
      //   128: iload 8
      //   130: sipush 200
      //   133: if_icmpne +18 -> 151
      //   136: iconst_0
      //   137: ifeq +14 -> 151
      //   140: aload_0
      //   141: getfield 46	com/intowow/sdk/b/d$b:b	Lcom/intowow/sdk/b/d$a;
      //   144: aconst_null
      //   145: invokeinterface 120 2 0
      //   150: return
      //   151: aload_0
      //   152: getfield 46	com/intowow/sdk/b/d$b:b	Lcom/intowow/sdk/b/d$a;
      //   155: iload 8
      //   157: invokeinterface 122 2 0
      //   162: return
      //   163: aload_1
      //   164: invokevirtual 125	java/net/HttpURLConnection:getContentEncoding	()Ljava/lang/String;
      //   167: astore_2
      //   168: new 23	java/lang/StringBuilder
      //   171: dup
      //   172: invokespecial 126	java/lang/StringBuilder:<init>	()V
      //   175: astore 6
      //   177: aload_2
      //   178: ifnull +141 -> 319
      //   181: aload_2
      //   182: invokevirtual 129	java/lang/String:toLowerCase	()Ljava/lang/String;
      //   185: ldc 99
      //   187: invokevirtual 133	java/lang/String:indexOf	(Ljava/lang/String;)I
      //   190: iconst_m1
      //   191: if_icmpeq +128 -> 319
      //   194: new 135	com/intowow/sdk/b/i
      //   197: dup
      //   198: aload_1
      //   199: invokevirtual 139	java/net/HttpURLConnection:getInputStream	()Ljava/io/InputStream;
      //   202: invokespecial 142	com/intowow/sdk/b/i:<init>	(Ljava/io/InputStream;)V
      //   205: astore_2
      //   206: aload_2
      //   207: astore 4
      //   209: aload_2
      //   210: astore_3
      //   211: new 144	java/io/BufferedReader
      //   214: dup
      //   215: new 146	java/io/InputStreamReader
      //   218: dup
      //   219: aload_2
      //   220: ldc 148
      //   222: invokespecial 151	java/io/InputStreamReader:<init>	(Ljava/io/InputStream;Ljava/lang/String;)V
      //   225: invokespecial 154	java/io/BufferedReader:<init>	(Ljava/io/Reader;)V
      //   228: astore 5
      //   230: aload_2
      //   231: astore 4
      //   233: aload_2
      //   234: astore_3
      //   235: aload 5
      //   237: invokevirtual 157	java/io/BufferedReader:readLine	()Ljava/lang/String;
      //   240: astore 7
      //   242: aload 7
      //   244: ifnonnull +100 -> 344
      //   247: aload_2
      //   248: astore 4
      //   250: aload_2
      //   251: astore_3
      //   252: new 159	org/json/JSONObject
      //   255: dup
      //   256: aload 6
      //   258: invokevirtual 42	java/lang/StringBuilder:toString	()Ljava/lang/String;
      //   261: invokespecial 160	org/json/JSONObject:<init>	(Ljava/lang/String;)V
      //   264: astore 5
      //   266: iconst_0
      //   267: ifeq +11 -> 278
      //   270: new 111	java/lang/NullPointerException
      //   273: dup
      //   274: invokespecial 112	java/lang/NullPointerException:<init>	()V
      //   277: athrow
      //   278: aload_2
      //   279: ifnull +7 -> 286
      //   282: aload_2
      //   283: invokevirtual 165	java/io/InputStream:close	()V
      //   286: aload_1
      //   287: ifnull +7 -> 294
      //   290: aload_1
      //   291: invokevirtual 115	java/net/HttpURLConnection:disconnect	()V
      //   294: iload 8
      //   296: sipush 200
      //   299: if_icmpne +204 -> 503
      //   302: aload 5
      //   304: ifnull +199 -> 503
      //   307: aload_0
      //   308: getfield 46	com/intowow/sdk/b/d$b:b	Lcom/intowow/sdk/b/d$a;
      //   311: aload 5
      //   313: invokeinterface 120 2 0
      //   318: return
      //   319: new 144	java/io/BufferedReader
      //   322: dup
      //   323: new 146	java/io/InputStreamReader
      //   326: dup
      //   327: aload_1
      //   328: invokevirtual 139	java/net/HttpURLConnection:getInputStream	()Ljava/io/InputStream;
      //   331: invokespecial 166	java/io/InputStreamReader:<init>	(Ljava/io/InputStream;)V
      //   334: invokespecial 154	java/io/BufferedReader:<init>	(Ljava/io/Reader;)V
      //   337: astore 5
      //   339: aconst_null
      //   340: astore_2
      //   341: goto -111 -> 230
      //   344: aload_2
      //   345: astore 4
      //   347: aload_2
      //   348: astore_3
      //   349: aload 6
      //   351: aload 7
      //   353: invokevirtual 38	java/lang/StringBuilder:append	(Ljava/lang/String;)Ljava/lang/StringBuilder;
      //   356: pop
      //   357: goto -127 -> 230
      //   360: astore_2
      //   361: aload_1
      //   362: astore_2
      //   363: aload 4
      //   365: astore_1
      //   366: iconst_0
      //   367: ifeq +11 -> 378
      //   370: new 111	java/lang/NullPointerException
      //   373: dup
      //   374: invokespecial 112	java/lang/NullPointerException:<init>	()V
      //   377: athrow
      //   378: aload_1
      //   379: ifnull +7 -> 386
      //   382: aload_1
      //   383: invokevirtual 165	java/io/InputStream:close	()V
      //   386: aload_2
      //   387: ifnull +7 -> 394
      //   390: aload_2
      //   391: invokevirtual 115	java/net/HttpURLConnection:disconnect	()V
      //   394: iload 8
      //   396: sipush 200
      //   399: if_icmpne +18 -> 417
      //   402: iconst_0
      //   403: ifeq +14 -> 417
      //   406: aload_0
      //   407: getfield 46	com/intowow/sdk/b/d$b:b	Lcom/intowow/sdk/b/d$a;
      //   410: aconst_null
      //   411: invokeinterface 120 2 0
      //   416: return
      //   417: aload_0
      //   418: getfield 46	com/intowow/sdk/b/d$b:b	Lcom/intowow/sdk/b/d$a;
      //   421: iload 8
      //   423: invokeinterface 122 2 0
      //   428: return
      //   429: astore_1
      //   430: iconst_m1
      //   431: istore 8
      //   433: aconst_null
      //   434: astore_3
      //   435: aconst_null
      //   436: astore_2
      //   437: iconst_0
      //   438: ifeq +11 -> 449
      //   441: new 111	java/lang/NullPointerException
      //   444: dup
      //   445: invokespecial 112	java/lang/NullPointerException:<init>	()V
      //   448: athrow
      //   449: aload_2
      //   450: ifnull +7 -> 457
      //   453: aload_2
      //   454: invokevirtual 165	java/io/InputStream:close	()V
      //   457: aload_3
      //   458: ifnull +7 -> 465
      //   461: aload_3
      //   462: invokevirtual 115	java/net/HttpURLConnection:disconnect	()V
      //   465: iload 8
      //   467: sipush 200
      //   470: if_icmpne +19 -> 489
      //   473: iconst_0
      //   474: ifeq +15 -> 489
      //   477: aload_0
      //   478: getfield 46	com/intowow/sdk/b/d$b:b	Lcom/intowow/sdk/b/d$a;
      //   481: aconst_null
      //   482: invokeinterface 120 2 0
      //   487: aload_1
      //   488: athrow
      //   489: aload_0
      //   490: getfield 46	com/intowow/sdk/b/d$b:b	Lcom/intowow/sdk/b/d$a;
      //   493: iload 8
      //   495: invokeinterface 122 2 0
      //   500: goto -13 -> 487
      //   503: aload_0
      //   504: getfield 46	com/intowow/sdk/b/d$b:b	Lcom/intowow/sdk/b/d$a;
      //   507: iload 8
      //   509: invokeinterface 122 2 0
      //   514: return
      //   515: astore_2
      //   516: goto -408 -> 108
      //   519: astore_2
      //   520: goto -400 -> 120
      //   523: astore_3
      //   524: goto -146 -> 378
      //   527: astore_1
      //   528: goto -142 -> 386
      //   531: astore 4
      //   533: goto -84 -> 449
      //   536: astore_2
      //   537: goto -80 -> 457
      //   540: astore_3
      //   541: goto -263 -> 278
      //   544: astore_2
      //   545: goto -259 -> 286
      //   548: astore_2
      //   549: aload_1
      //   550: astore_3
      //   551: aload_2
      //   552: astore_1
      //   553: iconst_m1
      //   554: istore 8
      //   556: aconst_null
      //   557: astore_2
      //   558: goto -121 -> 437
      //   561: astore_2
      //   562: aload_1
      //   563: astore_3
      //   564: aload_2
      //   565: astore_1
      //   566: aconst_null
      //   567: astore_2
      //   568: goto -131 -> 437
      //   571: astore_2
      //   572: aload_1
      //   573: astore 4
      //   575: aload_2
      //   576: astore_1
      //   577: aload_3
      //   578: astore_2
      //   579: aload 4
      //   581: astore_3
      //   582: goto -145 -> 437
      //   585: astore_1
      //   586: aconst_null
      //   587: astore_1
      //   588: aconst_null
      //   589: astore_2
      //   590: iload 9
      //   592: istore 8
      //   594: goto -228 -> 366
      //   597: astore_2
      //   598: aload_1
      //   599: astore_2
      //   600: aconst_null
      //   601: astore_1
      //   602: iload 9
      //   604: istore 8
      //   606: goto -240 -> 366
      //   609: astore_2
      //   610: aload_1
      //   611: astore_2
      //   612: aconst_null
      //   613: astore_1
      //   614: goto -248 -> 366
      //
      // Exception table:
      //   from	to	target	type
      //   211	230	360	java/lang/Exception
      //   235	242	360	java/lang/Exception
      //   252	266	360	java/lang/Exception
      //   349	357	360	java/lang/Exception
      //   3	37	429	finally
      //   37	45	429	finally
      //   100	108	515	java/io/IOException
      //   112	120	519	java/io/IOException
      //   370	378	523	java/io/IOException
      //   382	386	527	java/io/IOException
      //   441	449	531	java/io/IOException
      //   453	457	536	java/io/IOException
      //   270	278	540	java/io/IOException
      //   282	286	544	java/io/IOException
      //   45	88	548	finally
      //   163	177	561	finally
      //   181	206	561	finally
      //   319	339	561	finally
      //   211	230	571	finally
      //   235	242	571	finally
      //   252	266	571	finally
      //   349	357	571	finally
      //   3	37	585	java/lang/Exception
      //   37	45	585	java/lang/Exception
      //   45	88	597	java/lang/Exception
      //   163	177	609	java/lang/Exception
      //   181	206	609	java/lang/Exception
      //   319	339	609	java/lang/Exception
    }
  }
}

/* Location:           C:\Users\User\dex2jar-2.0\dex\qting\classes-dex2jar.jar
 * Qualified Name:     com.intowow.sdk.b.d
 * JD-Core Version:    0.6.2
 */