package com.miaozhen.mzmonitor;

import android.content.Context;
import android.content.SharedPreferences;
import android.content.SharedPreferences.Editor;

public final class j
{
  static long a;
  static int b = 0;
  private static Thread c;

  public static int a(Context paramContext)
  {
    return paramContext.getSharedPreferences("mzSdkProfilePrefs", 0).getInt("mzMaxLogItems", 100);
  }

  @Deprecated
  public static void a(Context paramContext, String paramString)
  {
    paramContext = paramContext.getSharedPreferences("mzSdkProfilePrefs", 0).edit();
    paramContext.putString("mzProfileURI", paramString);
    paramContext.commit();
  }

  static void a(Context paramContext, String paramString1, String paramString2)
  {
    if (paramString1 != null)
    {
      paramContext = paramContext.getSharedPreferences("mzSdkProfilePrefs", 0).edit();
      paramContext.putString("mzLatestLocation", paramString1);
      paramContext.putString("latestLocation", paramString2);
      paramContext.putLong("mzLocationUpdateTimestamp", c.a.a());
      paramContext.commit();
    }
  }

  public static int b(Context paramContext)
  {
    return paramContext.getSharedPreferences("mzSdkProfilePrefs", 0).getInt("mzMaxLogRetryTime", 20);
  }

  public static int c(Context paramContext)
  {
    return paramContext.getSharedPreferences("mzSdkProfilePrefs", 0).getInt("mzProfileVersion", 1);
  }

  public static String d(Context paramContext)
  {
    return paramContext.getSharedPreferences("mzSdkProfilePrefs", 0).getString("mzSignVersion", "1.1");
  }

  public static int e(Context paramContext)
  {
    return paramContext.getSharedPreferences("mzSdkProfilePrefs", 0).getInt("mzLogExpiresIn", 604800);
  }

  public static int f(Context paramContext)
  {
    return paramContext.getSharedPreferences("mzSdkProfilePrefs", 0).getInt("mzLocationServiceTimeout", 15);
  }

  public static String g(Context paramContext)
  {
    return paramContext.getSharedPreferences("mzSdkProfilePrefs", 0).getString("mzLatestLocation", "[UNKNOWN]");
  }

  static String h(Context paramContext)
  {
    return paramContext.getSharedPreferences("mzSdkProfilePrefs", 0).getString("latestLocation", "0x0");
  }

  public static boolean i(Context paramContext)
  {
    boolean bool = false;
    paramContext = paramContext.getSharedPreferences("mzSdkProfilePrefs", 0);
    if (paramContext.getString("mzConfigFile", null) == null)
      bool = true;
    long l;
    do
    {
      return bool;
      l = c.a.a();
    }
    while (l - paramContext.getLong("mzProfileUpdateTimestamp", l) < paramContext.getInt("mzProfileExpiresIn", 86400));
    return true;
  }

  public static boolean j(Context paramContext)
  {
    boolean bool = false;
    paramContext = paramContext.getSharedPreferences("mzSdkProfilePrefs", 0);
    long l1 = c.a.a();
    long l2 = paramContext.getLong("mzLocationUpdateTimestamp", l1);
    if (l2 == l1)
      bool = true;
    do
    {
      return bool;
      if (l1 - l2 >= paramContext.getInt("mzLocationExpiresIn", 300))
        return true;
    }
    while (!paramContext.getString("mzLatestLocation", "[UNKNOWN]").equals("[UNKNOWN]"));
    return true;
  }

  static String k(Context paramContext)
  {
    String str = paramContext.getSharedPreferences("mzSdkProfilePrefs", 0).getString("mzConfigFile", null);
    paramContext = str;
    if (str == null)
      paramContext = e.a;
    return paramContext;
  }

  static void l(Context paramContext)
  {
    if ((c != null) && (c.isAlive()))
      return;
    paramContext = new Thread()
    {
      // ERROR //
      public final void run()
      {
        // Byte code:
        //   0: invokestatic 26	com/miaozhen/mzmonitor/j:a	()Ljava/lang/Thread;
        //   3: astore 12
        //   5: aload 12
        //   7: monitorenter
        //   8: aconst_null
        //   9: astore 10
        //   11: aconst_null
        //   12: astore 11
        //   14: aconst_null
        //   15: astore 8
        //   17: aconst_null
        //   18: astore 6
        //   20: aconst_null
        //   21: astore 7
        //   23: aconst_null
        //   24: astore 9
        //   26: aload 7
        //   28: astore_3
        //   29: aload 10
        //   31: astore_2
        //   32: aload 11
        //   34: astore 4
        //   36: aload_0
        //   37: getfield 14	com/miaozhen/mzmonitor/j$1:a	Landroid/content/Context;
        //   40: ldc 28
        //   42: iconst_0
        //   43: invokevirtual 34	android/content/Context:getSharedPreferences	(Ljava/lang/String;I)Landroid/content/SharedPreferences;
        //   46: astore 13
        //   48: aload 7
        //   50: astore_3
        //   51: aload 10
        //   53: astore_2
        //   54: aload 11
        //   56: astore 4
        //   58: new 36	java/net/URL
        //   61: dup
        //   62: aload 13
        //   64: ldc 38
        //   66: ldc 40
        //   68: invokeinterface 46 3 0
        //   73: invokespecial 49	java/net/URL:<init>	(Ljava/lang/String;)V
        //   76: invokevirtual 53	java/net/URL:openConnection	()Ljava/net/URLConnection;
        //   79: checkcast 55	java/net/HttpURLConnection
        //   82: astore 14
        //   84: aload 7
        //   86: astore_3
        //   87: aload 10
        //   89: astore_2
        //   90: aload 11
        //   92: astore 4
        //   94: aload 14
        //   96: sipush 5000
        //   99: invokevirtual 59	java/net/HttpURLConnection:setConnectTimeout	(I)V
        //   102: aload 7
        //   104: astore_3
        //   105: aload 10
        //   107: astore_2
        //   108: aload 11
        //   110: astore 4
        //   112: aload 14
        //   114: iconst_0
        //   115: invokevirtual 63	java/net/HttpURLConnection:setUseCaches	(Z)V
        //   118: aload 7
        //   120: astore_3
        //   121: aload 10
        //   123: astore_2
        //   124: aload 11
        //   126: astore 4
        //   128: aload 14
        //   130: ldc 65
        //   132: invokevirtual 68	java/net/HttpURLConnection:setRequestMethod	(Ljava/lang/String;)V
        //   135: aload 7
        //   137: astore_3
        //   138: aload 10
        //   140: astore_2
        //   141: aload 11
        //   143: astore 4
        //   145: aload 14
        //   147: invokevirtual 71	java/net/HttpURLConnection:connect	()V
        //   150: aload 9
        //   152: astore 5
        //   154: aload 8
        //   156: astore_1
        //   157: aload 7
        //   159: astore_3
        //   160: aload 10
        //   162: astore_2
        //   163: aload 11
        //   165: astore 4
        //   167: aload 14
        //   169: invokevirtual 75	java/net/HttpURLConnection:getResponseCode	()I
        //   172: ifle +131 -> 303
        //   175: aload 9
        //   177: astore 5
        //   179: aload 8
        //   181: astore_1
        //   182: aload 7
        //   184: astore_3
        //   185: aload 10
        //   187: astore_2
        //   188: aload 11
        //   190: astore 4
        //   192: aload 14
        //   194: invokevirtual 75	java/net/HttpURLConnection:getResponseCode	()I
        //   197: sipush 400
        //   200: if_icmpge +103 -> 303
        //   203: aload 7
        //   205: astore_3
        //   206: aload 10
        //   208: astore_2
        //   209: aload 11
        //   211: astore 4
        //   213: aload 14
        //   215: invokevirtual 79	java/net/HttpURLConnection:getInputStream	()Ljava/io/InputStream;
        //   218: astore_1
        //   219: aload 7
        //   221: astore_3
        //   222: aload_1
        //   223: astore_2
        //   224: aload_1
        //   225: astore 4
        //   227: new 81	java/io/BufferedReader
        //   230: dup
        //   231: new 83	java/io/InputStreamReader
        //   234: dup
        //   235: aload_1
        //   236: invokespecial 86	java/io/InputStreamReader:<init>	(Ljava/io/InputStream;)V
        //   239: invokespecial 89	java/io/BufferedReader:<init>	(Ljava/io/Reader;)V
        //   242: astore 5
        //   244: new 91	java/lang/StringBuffer
        //   247: dup
        //   248: invokespecial 92	java/lang/StringBuffer:<init>	()V
        //   251: astore_2
        //   252: aload 5
        //   254: invokevirtual 96	java/io/BufferedReader:readLine	()Ljava/lang/String;
        //   257: astore_3
        //   258: aload_3
        //   259: ifnonnull +66 -> 325
        //   262: aload 13
        //   264: invokeinterface 100 1 0
        //   269: ldc 102
        //   271: aload_2
        //   272: invokevirtual 105	java/lang/StringBuffer:toString	()Ljava/lang/String;
        //   275: invokeinterface 111 3 0
        //   280: invokeinterface 115 1 0
        //   285: pop
        //   286: aload_0
        //   287: getfield 14	com/miaozhen/mzmonitor/j$1:a	Landroid/content/Context;
        //   290: invokestatic 118	com/miaozhen/mzmonitor/j:m	(Landroid/content/Context;)V
        //   293: aload_0
        //   294: getfield 14	com/miaozhen/mzmonitor/j$1:a	Landroid/content/Context;
        //   297: invokestatic 123	com/miaozhen/mzmonitor/c:a	(Landroid/content/Context;)Lcom/miaozhen/mzmonitor/c;
        //   300: invokevirtual 126	com/miaozhen/mzmonitor/c:b	()V
        //   303: aload_1
        //   304: ifnull +7 -> 311
        //   307: aload_1
        //   308: invokevirtual 131	java/io/InputStream:close	()V
        //   311: aload 5
        //   313: ifnull +8 -> 321
        //   316: aload 5
        //   318: invokevirtual 132	java/io/BufferedReader:close	()V
        //   321: aload 12
        //   323: monitorexit
        //   324: return
        //   325: aload_2
        //   326: aload_3
        //   327: invokevirtual 136	java/lang/StringBuffer:append	(Ljava/lang/String;)Ljava/lang/StringBuffer;
        //   330: pop
        //   331: goto -79 -> 252
        //   334: astore_3
        //   335: aload 5
        //   337: astore_2
        //   338: aload_1
        //   339: astore 4
        //   341: aload_3
        //   342: astore 5
        //   344: aload_2
        //   345: astore_1
        //   346: aload_1
        //   347: astore_3
        //   348: aload 4
        //   350: astore_2
        //   351: ldc 138
        //   353: new 140	java/lang/StringBuilder
        //   356: dup
        //   357: ldc 142
        //   359: invokespecial 143	java/lang/StringBuilder:<init>	(Ljava/lang/String;)V
        //   362: aload 5
        //   364: invokevirtual 146	java/lang/StringBuilder:append	(Ljava/lang/Object;)Ljava/lang/StringBuilder;
        //   367: invokevirtual 147	java/lang/StringBuilder:toString	()Ljava/lang/String;
        //   370: invokestatic 153	android/util/Log:d	(Ljava/lang/String;Ljava/lang/String;)I
        //   373: pop
        //   374: aload 4
        //   376: ifnull +8 -> 384
        //   379: aload 4
        //   381: invokevirtual 131	java/io/InputStream:close	()V
        //   384: aload_1
        //   385: ifnull -64 -> 321
        //   388: aload_1
        //   389: invokevirtual 132	java/io/BufferedReader:close	()V
        //   392: goto -71 -> 321
        //   395: astore_1
        //   396: aload_1
        //   397: invokevirtual 156	java/io/IOException:printStackTrace	()V
        //   400: goto -79 -> 321
        //   403: astore_1
        //   404: aload 12
        //   406: monitorexit
        //   407: aload_1
        //   408: athrow
        //   409: astore_1
        //   410: aload_2
        //   411: ifnull +7 -> 418
        //   414: aload_2
        //   415: invokevirtual 131	java/io/InputStream:close	()V
        //   418: aload_3
        //   419: ifnull +7 -> 426
        //   422: aload_3
        //   423: invokevirtual 132	java/io/BufferedReader:close	()V
        //   426: aload_1
        //   427: athrow
        //   428: astore_2
        //   429: aload_2
        //   430: invokevirtual 156	java/io/IOException:printStackTrace	()V
        //   433: goto -7 -> 426
        //   436: astore_1
        //   437: aload_1
        //   438: invokevirtual 156	java/io/IOException:printStackTrace	()V
        //   441: goto -120 -> 321
        //   444: astore 4
        //   446: aload 5
        //   448: astore_3
        //   449: aload_1
        //   450: astore_2
        //   451: aload 4
        //   453: astore_1
        //   454: goto -44 -> 410
        //   457: astore 5
        //   459: aload 6
        //   461: astore_1
        //   462: goto -116 -> 346
        //
        // Exception table:
        //   from	to	target	type
        //   244	252	334	java/lang/Exception
        //   252	258	334	java/lang/Exception
        //   262	303	334	java/lang/Exception
        //   325	331	334	java/lang/Exception
        //   379	384	395	java/io/IOException
        //   388	392	395	java/io/IOException
        //   307	311	403	finally
        //   316	321	403	finally
        //   321	324	403	finally
        //   379	384	403	finally
        //   388	392	403	finally
        //   396	400	403	finally
        //   414	418	403	finally
        //   422	426	403	finally
        //   426	428	403	finally
        //   429	433	403	finally
        //   437	441	403	finally
        //   36	48	409	finally
        //   58	84	409	finally
        //   94	102	409	finally
        //   112	118	409	finally
        //   128	135	409	finally
        //   145	150	409	finally
        //   167	175	409	finally
        //   192	203	409	finally
        //   213	219	409	finally
        //   227	244	409	finally
        //   351	374	409	finally
        //   414	418	428	java/io/IOException
        //   422	426	428	java/io/IOException
        //   307	311	436	java/io/IOException
        //   316	321	436	java/io/IOException
        //   244	252	444	finally
        //   252	258	444	finally
        //   262	303	444	finally
        //   325	331	444	finally
        //   36	48	457	java/lang/Exception
        //   58	84	457	java/lang/Exception
        //   94	102	457	java/lang/Exception
        //   112	118	457	java/lang/Exception
        //   128	135	457	java/lang/Exception
        //   145	150	457	java/lang/Exception
        //   167	175	457	java/lang/Exception
        //   192	203	457	java/lang/Exception
        //   213	219	457	java/lang/Exception
        //   227	244	457	java/lang/Exception
      }
    };
    c = paramContext;
    paramContext.start();
  }

  // ERROR //
  static void m(Context paramContext)
  {
    // Byte code:
    //   0: aconst_null
    //   1: astore_3
    //   2: aconst_null
    //   3: astore_2
    //   4: aload_3
    //   5: astore_1
    //   6: aload_0
    //   7: ldc 20
    //   9: iconst_0
    //   10: invokevirtual 26	android/content/Context:getSharedPreferences	(Ljava/lang/String;I)Landroid/content/SharedPreferences;
    //   13: astore 4
    //   15: aload_3
    //   16: astore_1
    //   17: new 147	java/io/ByteArrayInputStream
    //   20: dup
    //   21: aload 4
    //   23: ldc 103
    //   25: aconst_null
    //   26: invokeinterface 86 3 0
    //   31: ldc 149
    //   33: invokevirtual 153	java/lang/String:getBytes	(Ljava/lang/String;)[B
    //   36: invokespecial 156	java/io/ByteArrayInputStream:<init>	([B)V
    //   39: astore_0
    //   40: invokestatic 162	android/util/Xml:newPullParser	()Lorg/xmlpull/v1/XmlPullParser;
    //   43: astore_3
    //   44: aload_3
    //   45: aload_0
    //   46: ldc 149
    //   48: invokeinterface 168 3 0
    //   53: aconst_null
    //   54: astore_1
    //   55: aload_3
    //   56: invokeinterface 172 1 0
    //   61: istore 9
    //   63: iconst_0
    //   64: istore 10
    //   66: iconst_0
    //   67: istore 6
    //   69: goto +582 -> 651
    //   72: aload 4
    //   74: invokeinterface 43 1 0
    //   79: astore_2
    //   80: aload_1
    //   81: ldc 174
    //   83: invokeinterface 179 2 0
    //   88: ifeq +26 -> 114
    //   91: aload_2
    //   92: ldc 76
    //   94: aload_1
    //   95: ldc 174
    //   97: invokeinterface 183 2 0
    //   102: checkcast 117	java/lang/String
    //   105: invokestatic 189	java/lang/Integer:parseInt	(Ljava/lang/String;)I
    //   108: invokeinterface 193 3 0
    //   113: pop
    //   114: aload_1
    //   115: ldc 195
    //   117: invokeinterface 179 2 0
    //   122: ifeq +23 -> 145
    //   125: aload_2
    //   126: ldc 80
    //   128: aload_1
    //   129: ldc 195
    //   131: invokeinterface 183 2 0
    //   136: checkcast 117	java/lang/String
    //   139: invokeinterface 51 3 0
    //   144: pop
    //   145: aload_1
    //   146: ldc 197
    //   148: invokeinterface 179 2 0
    //   153: ifeq +26 -> 179
    //   156: aload_2
    //   157: ldc 111
    //   159: aload_1
    //   160: ldc 197
    //   162: invokeinterface 183 2 0
    //   167: checkcast 117	java/lang/String
    //   170: invokestatic 189	java/lang/Integer:parseInt	(Ljava/lang/String;)I
    //   173: invokeinterface 193 3 0
    //   178: pop
    //   179: aload_1
    //   180: ldc 199
    //   182: invokeinterface 179 2 0
    //   187: ifeq +26 -> 213
    //   190: aload_2
    //   191: ldc 89
    //   193: aload_1
    //   194: ldc 199
    //   196: invokeinterface 183 2 0
    //   201: checkcast 117	java/lang/String
    //   204: invokestatic 189	java/lang/Integer:parseInt	(Ljava/lang/String;)I
    //   207: invokeinterface 193 3 0
    //   212: pop
    //   213: aload_1
    //   214: ldc 201
    //   216: invokeinterface 179 2 0
    //   221: ifeq +26 -> 247
    //   224: aload_2
    //   225: ldc 28
    //   227: aload_1
    //   228: ldc 201
    //   230: invokeinterface 183 2 0
    //   235: checkcast 117	java/lang/String
    //   238: invokestatic 189	java/lang/Integer:parseInt	(Ljava/lang/String;)I
    //   241: invokeinterface 193 3 0
    //   246: pop
    //   247: aload_1
    //   248: ldc 203
    //   250: invokeinterface 179 2 0
    //   255: ifeq +26 -> 281
    //   258: aload_2
    //   259: ldc 74
    //   261: aload_1
    //   262: ldc 203
    //   264: invokeinterface 183 2 0
    //   269: checkcast 117	java/lang/String
    //   272: invokestatic 189	java/lang/Integer:parseInt	(Ljava/lang/String;)I
    //   275: invokeinterface 193 3 0
    //   280: pop
    //   281: aload_1
    //   282: ldc 205
    //   284: invokeinterface 179 2 0
    //   289: ifeq +26 -> 315
    //   292: aload_2
    //   293: ldc 115
    //   295: aload_1
    //   296: ldc 205
    //   298: invokeinterface 183 2 0
    //   303: checkcast 117	java/lang/String
    //   306: invokestatic 189	java/lang/Integer:parseInt	(Ljava/lang/String;)I
    //   309: invokeinterface 193 3 0
    //   314: pop
    //   315: aload_1
    //   316: ldc 207
    //   318: invokeinterface 179 2 0
    //   323: ifeq +26 -> 349
    //   326: aload_2
    //   327: ldc 93
    //   329: aload_1
    //   330: ldc 207
    //   332: invokeinterface 183 2 0
    //   337: checkcast 117	java/lang/String
    //   340: invokestatic 189	java/lang/Integer:parseInt	(Ljava/lang/String;)I
    //   343: invokeinterface 193 3 0
    //   348: pop
    //   349: aload_2
    //   350: ldc 105
    //   352: invokestatic 68	com/miaozhen/mzmonitor/c$a:a	()J
    //   355: invokeinterface 72 4 0
    //   360: pop
    //   361: aload_2
    //   362: invokeinterface 55 1 0
    //   367: pop
    //   368: aload_0
    //   369: invokevirtual 212	java/io/InputStream:close	()V
    //   372: return
    //   373: iload 6
    //   375: ifne -303 -> 72
    //   378: iload 6
    //   380: istore 7
    //   382: aload_1
    //   383: astore_2
    //   384: iload 10
    //   386: istore 8
    //   388: iload 9
    //   390: tableswitch	default:+30 -> 420, 0:+61->451, 1:+40->430, 2:+80->470, 3:+140->530
    //   421: lconst_1
    //   422: istore 8
    //   424: aload_1
    //   425: astore_2
    //   426: iload 6
    //   428: istore 7
    //   430: aload_3
    //   431: invokeinterface 215 1 0
    //   436: istore 9
    //   438: iload 7
    //   440: istore 6
    //   442: aload_2
    //   443: astore_1
    //   444: iload 8
    //   446: istore 10
    //   448: goto +203 -> 651
    //   451: new 217	java/util/HashMap
    //   454: dup
    //   455: invokespecial 219	java/util/HashMap:<init>	()V
    //   458: astore_2
    //   459: iload 6
    //   461: istore 7
    //   463: iload 10
    //   465: istore 8
    //   467: goto -37 -> 430
    //   470: aload_3
    //   471: invokeinterface 223 1 0
    //   476: astore 5
    //   478: iload 10
    //   480: ifeq +18 -> 498
    //   483: aload_1
    //   484: aload 5
    //   486: aload_3
    //   487: invokeinterface 226 1 0
    //   492: invokeinterface 230 3 0
    //   497: pop
    //   498: iload 6
    //   500: istore 7
    //   502: aload_1
    //   503: astore_2
    //   504: iload 10
    //   506: istore 8
    //   508: aload 5
    //   510: ldc 232
    //   512: invokevirtual 121	java/lang/String:equals	(Ljava/lang/Object;)Z
    //   515: ifeq -85 -> 430
    //   518: iconst_1
    //   519: istore 8
    //   521: iload 6
    //   523: istore 7
    //   525: aload_1
    //   526: astore_2
    //   527: goto -97 -> 430
    //   530: aload_3
    //   531: invokeinterface 223 1 0
    //   536: ldc 232
    //   538: invokevirtual 121	java/lang/String:equals	(Ljava/lang/Object;)Z
    //   541: istore 11
    //   543: iload 6
    //   545: istore 7
    //   547: aload_1
    //   548: astore_2
    //   549: iload 10
    //   551: istore 8
    //   553: iload 11
    //   555: ifeq -125 -> 430
    //   558: iconst_1
    //   559: istore 7
    //   561: aload_1
    //   562: astore_2
    //   563: iload 10
    //   565: istore 8
    //   567: goto -137 -> 430
    //   570: astore_1
    //   571: aload_2
    //   572: astore_0
    //   573: aload_1
    //   574: astore_2
    //   575: aload_0
    //   576: astore_1
    //   577: ldc 234
    //   579: new 236	java/lang/StringBuilder
    //   582: dup
    //   583: ldc 238
    //   585: invokespecial 241	java/lang/StringBuilder:<init>	(Ljava/lang/String;)V
    //   588: aload_2
    //   589: invokevirtual 245	java/lang/StringBuilder:append	(Ljava/lang/Object;)Ljava/lang/StringBuilder;
    //   592: invokevirtual 248	java/lang/StringBuilder:toString	()Ljava/lang/String;
    //   595: invokestatic 253	android/util/Log:d	(Ljava/lang/String;Ljava/lang/String;)I
    //   598: pop
    //   599: aload_0
    //   600: ifnull -228 -> 372
    //   603: aload_0
    //   604: invokevirtual 212	java/io/InputStream:close	()V
    //   607: return
    //   608: astore_0
    //   609: aload_0
    //   610: invokevirtual 256	java/io/IOException:printStackTrace	()V
    //   613: return
    //   614: astore_0
    //   615: aload_1
    //   616: ifnull +7 -> 623
    //   619: aload_1
    //   620: invokevirtual 212	java/io/InputStream:close	()V
    //   623: aload_0
    //   624: athrow
    //   625: astore_1
    //   626: aload_1
    //   627: invokevirtual 256	java/io/IOException:printStackTrace	()V
    //   630: goto -7 -> 623
    //   633: astore_0
    //   634: aload_0
    //   635: invokevirtual 256	java/io/IOException:printStackTrace	()V
    //   638: return
    //   639: astore_2
    //   640: aload_0
    //   641: astore_1
    //   642: aload_2
    //   643: astore_0
    //   644: goto -29 -> 615
    //   647: astore_2
    //   648: goto -73 -> 575
    //   651: iload 9
    //   653: iconst_1
    //   654: if_icmpne -281 -> 373
    //   657: goto -585 -> 72
    //
    // Exception table:
    //   from	to	target	type
    //   6	15	570	java/lang/Exception
    //   17	40	570	java/lang/Exception
    //   603	607	608	java/io/IOException
    //   6	15	614	finally
    //   17	40	614	finally
    //   577	599	614	finally
    //   619	623	625	java/io/IOException
    //   368	372	633	java/io/IOException
    //   40	53	639	finally
    //   55	63	639	finally
    //   72	114	639	finally
    //   114	145	639	finally
    //   145	179	639	finally
    //   179	213	639	finally
    //   213	247	639	finally
    //   247	281	639	finally
    //   281	315	639	finally
    //   315	349	639	finally
    //   349	368	639	finally
    //   430	438	639	finally
    //   451	459	639	finally
    //   470	478	639	finally
    //   483	498	639	finally
    //   508	518	639	finally
    //   530	543	639	finally
    //   40	53	647	java/lang/Exception
    //   55	63	647	java/lang/Exception
    //   72	114	647	java/lang/Exception
    //   114	145	647	java/lang/Exception
    //   145	179	647	java/lang/Exception
    //   179	213	647	java/lang/Exception
    //   213	247	647	java/lang/Exception
    //   247	281	647	java/lang/Exception
    //   281	315	647	java/lang/Exception
    //   315	349	647	java/lang/Exception
    //   349	368	647	java/lang/Exception
    //   430	438	647	java/lang/Exception
    //   451	459	647	java/lang/Exception
    //   470	478	647	java/lang/Exception
    //   483	498	647	java/lang/Exception
    //   508	518	647	java/lang/Exception
    //   530	543	647	java/lang/Exception
  }
}

/* Location:           C:\Users\User\dex2jar-2.0\dex\qting\classes-dex2jar.jar
 * Qualified Name:     com.miaozhen.mzmonitor.j
 * JD-Core Version:    0.6.2
 */